{
"meta":{"test_sets":[],"test_metrics":[],"learn_metrics":[{"best_value":"Min","name":"Logloss"}],"launch_mode":"Train","parameters":"","iteration_count":1000,"learn_sets":["learn"],"name":"experiment"},
"iterations":[
{"learn":[0.600617631],"iteration":0,"passed_time":0.3416160737,"remaining_time":341.2744577},
{"learn":[0.5121751557],"iteration":1,"passed_time":0.5460262661,"remaining_time":272.4671068},
{"learn":[0.4422659154],"iteration":2,"passed_time":0.7141808712,"remaining_time":237.3461095},
{"learn":[0.3877673241],"iteration":3,"passed_time":0.8826534351,"remaining_time":219.7807053},
{"learn":[0.3437251375],"iteration":4,"passed_time":1.056727441,"remaining_time":210.2887607},
{"learn":[0.3088607097],"iteration":5,"passed_time":1.228813664,"remaining_time":203.5734636},
{"learn":[0.2786099309],"iteration":6,"passed_time":1.412945089,"remaining_time":200.4363533},
{"learn":[0.2518316019],"iteration":7,"passed_time":1.58350358,"remaining_time":196.3544439},
{"learn":[0.2292075838],"iteration":8,"passed_time":1.747315264,"remaining_time":192.3988252},
{"learn":[0.2089079852],"iteration":9,"passed_time":1.912615789,"remaining_time":189.3489631},
{"learn":[0.1934459085],"iteration":10,"passed_time":2.072315183,"remaining_time":186.3199742},
{"learn":[0.1805833746],"iteration":11,"passed_time":2.238691359,"remaining_time":184.3189219},
{"learn":[0.1699587381],"iteration":12,"passed_time":2.388519788,"remaining_time":181.3437716},
{"learn":[0.159721673],"iteration":13,"passed_time":2.557287698,"remaining_time":180.1061193},
{"learn":[0.1512331464],"iteration":14,"passed_time":2.706170504,"remaining_time":177.7051964},
{"learn":[0.1432949876],"iteration":15,"passed_time":2.856736961,"remaining_time":175.6893231},
{"learn":[0.1371530643],"iteration":16,"passed_time":3.257277346,"remaining_time":188.3472724},
{"learn":[0.1319247182],"iteration":17,"passed_time":3.413447535,"remaining_time":186.2225266},
{"learn":[0.1274884229],"iteration":18,"passed_time":3.569404207,"remaining_time":184.2939751},
{"learn":[0.1238132131],"iteration":19,"passed_time":3.739694532,"remaining_time":183.2450321},
{"learn":[0.1191632398],"iteration":20,"passed_time":3.89278862,"remaining_time":181.4780981},
{"learn":[0.1152697483],"iteration":21,"passed_time":4.054010573,"remaining_time":180.2191973},
{"learn":[0.1102230134],"iteration":22,"passed_time":4.204942259,"remaining_time":178.6186342},
{"learn":[0.1073231019],"iteration":23,"passed_time":4.364845677,"remaining_time":177.5037242},
{"learn":[0.1046923167],"iteration":24,"passed_time":4.512741093,"remaining_time":175.9969026},
{"learn":[0.102224001],"iteration":25,"passed_time":4.657037255,"remaining_time":174.4597802},
{"learn":[0.09953590451],"iteration":26,"passed_time":4.809938772,"remaining_time":173.3359417},
{"learn":[0.09777131399],"iteration":27,"passed_time":4.949610184,"remaining_time":171.8221821},
{"learn":[0.09604563823],"iteration":28,"passed_time":5.101767181,"remaining_time":170.8212391},
{"learn":[0.09469044808],"iteration":29,"passed_time":5.256288674,"remaining_time":169.9533338},
{"learn":[0.09266305764],"iteration":30,"passed_time":5.422158842,"remaining_time":169.4861909},
{"learn":[0.09118616026],"iteration":31,"passed_time":5.574270185,"remaining_time":168.6216731},
{"learn":[0.08987779547],"iteration":32,"passed_time":5.730335979,"remaining_time":167.9162088},
{"learn":[0.08809819632],"iteration":33,"passed_time":5.884173113,"remaining_time":167.179742},
{"learn":[0.08700676112],"iteration":34,"passed_time":6.039021392,"remaining_time":166.504447},
{"learn":[0.08593925502],"iteration":35,"passed_time":6.187979842,"remaining_time":165.7003491},
{"learn":[0.08478519311],"iteration":36,"passed_time":6.345168881,"remaining_time":165.145882},
{"learn":[0.08403040594],"iteration":37,"passed_time":6.498849757,"remaining_time":164.5235123},
{"learn":[0.08261011707],"iteration":38,"passed_time":6.652025228,"remaining_time":163.9127242},
{"learn":[0.08078644798],"iteration":39,"passed_time":6.789453474,"remaining_time":162.9468834},
{"learn":[0.08018219108],"iteration":40,"passed_time":6.926874915,"remaining_time":162.0212938},
{"learn":[0.07913403878],"iteration":41,"passed_time":7.080083392,"remaining_time":161.4933307},
{"learn":[0.07840375479],"iteration":42,"passed_time":7.214424976,"remaining_time":160.5629},
{"learn":[0.07706540312],"iteration":43,"passed_time":7.365426756,"remaining_time":160.0306359},
{"learn":[0.0763329533],"iteration":44,"passed_time":7.514010859,"remaining_time":159.4640082},
{"learn":[0.07491528948],"iteration":45,"passed_time":7.657960828,"remaining_time":158.8194485},
{"learn":[0.07283043827],"iteration":46,"passed_time":7.813796902,"remaining_time":158.437201},
{"learn":[0.0721943851],"iteration":47,"passed_time":7.958617065,"remaining_time":157.8459051},
{"learn":[0.07122813011],"iteration":48,"passed_time":8.107691898,"remaining_time":157.3554081},
{"learn":[0.07067524394],"iteration":49,"passed_time":8.253682822,"remaining_time":156.8199736},
{"learn":[0.06997631993],"iteration":50,"passed_time":8.399647789,"remaining_time":156.2993285},
{"learn":[0.06856137498],"iteration":51,"passed_time":8.56107585,"remaining_time":156.0749982},
{"learn":[0.0682089238],"iteration":52,"passed_time":8.695483616,"remaining_time":155.370245},
{"learn":[0.06746219685],"iteration":53,"passed_time":8.841268976,"remaining_time":154.8859343},
{"learn":[0.06690516797],"iteration":54,"passed_time":8.987880852,"remaining_time":154.4281346},
{"learn":[0.06608284356],"iteration":55,"passed_time":9.133256323,"remaining_time":153.9606066},
{"learn":[0.06578325055],"iteration":56,"passed_time":9.263728013,"remaining_time":153.2578161},
{"learn":[0.06525560674],"iteration":57,"passed_time":9.41503883,"remaining_time":152.9132169},
{"learn":[0.06485083939],"iteration":58,"passed_time":9.549638433,"remaining_time":152.3086401},
{"learn":[0.06432913157],"iteration":59,"passed_time":9.693531634,"remaining_time":151.8653289},
{"learn":[0.06397568196],"iteration":60,"passed_time":9.828882447,"remaining_time":151.300338},
{"learn":[0.06346266852],"iteration":61,"passed_time":9.972250447,"remaining_time":150.8704987},
{"learn":[0.06305978151],"iteration":62,"passed_time":10.11054976,"remaining_time":150.3743671},
{"learn":[0.06262802406],"iteration":63,"passed_time":10.2652785,"remaining_time":150.1296981},
{"learn":[0.06199789466],"iteration":64,"passed_time":10.41520834,"remaining_time":149.8187661},
{"learn":[0.0616716632],"iteration":65,"passed_time":10.55552396,"remaining_time":149.3766572},
{"learn":[0.06112053588],"iteration":66,"passed_time":10.69614841,"remaining_time":148.9478577},
{"learn":[0.06062963768],"iteration":67,"passed_time":10.8457224,"remaining_time":148.6501952},
{"learn":[0.06042848312],"iteration":68,"passed_time":10.97436683,"remaining_time":148.0744278},
{"learn":[0.05988711315],"iteration":69,"passed_time":11.13344719,"remaining_time":147.9157984},
{"learn":[0.05932876304],"iteration":70,"passed_time":11.28049919,"remaining_time":147.5997712},
{"learn":[0.05893640478],"iteration":71,"passed_time":11.42406497,"remaining_time":147.243504},
{"learn":[0.05856897335],"iteration":72,"passed_time":11.55728014,"remaining_time":146.7616258},
{"learn":[0.058241643],"iteration":73,"passed_time":11.68648166,"remaining_time":146.2389462},
{"learn":[0.05796151403],"iteration":74,"passed_time":11.82364252,"remaining_time":145.8249244},
{"learn":[0.05754424484],"iteration":75,"passed_time":11.95765515,"remaining_time":145.3799127},
{"learn":[0.05616590374],"iteration":76,"passed_time":12.11474444,"remaining_time":145.219599},
{"learn":[0.05570804425],"iteration":77,"passed_time":12.27768265,"remaining_time":145.1285051},
{"learn":[0.05553378023],"iteration":78,"passed_time":12.40560766,"remaining_time":144.6274007},
{"learn":[0.05512963789],"iteration":79,"passed_time":12.54858707,"remaining_time":144.3087513},
{"learn":[0.0547769463],"iteration":80,"passed_time":12.69149632,"remaining_time":143.9936435},
{"learn":[0.05430714129],"iteration":81,"passed_time":12.87245558,"remaining_time":144.10871},
{"learn":[0.05403029079],"iteration":82,"passed_time":13.06867169,"remaining_time":144.3852041},
{"learn":[0.05354641395],"iteration":83,"passed_time":13.23027399,"remaining_time":144.2729878},
{"learn":[0.05330114539],"iteration":84,"passed_time":13.41248124,"remaining_time":144.3814157},
{"learn":[0.05310196656],"iteration":85,"passed_time":13.64664412,"remaining_time":145.0352643},
{"learn":[0.05249737943],"iteration":86,"passed_time":13.89010757,"remaining_time":145.7663013},
{"learn":[0.05189798693],"iteration":87,"passed_time":14.15442497,"remaining_time":146.6913133},
{"learn":[0.05137147378],"iteration":88,"passed_time":14.43081024,"remaining_time":147.713125},
{"learn":[0.05111420877],"iteration":89,"passed_time":14.67670659,"remaining_time":148.3978111},
{"learn":[0.05087776641],"iteration":90,"passed_time":14.82824733,"remaining_time":148.1195255},
{"learn":[0.05068453596],"iteration":91,"passed_time":14.95863128,"remaining_time":147.635187},
{"learn":[0.05054076358],"iteration":92,"passed_time":15.09709521,"remaining_time":147.2372619},
{"learn":[0.05030975327],"iteration":93,"passed_time":15.23116726,"remaining_time":146.802527},
{"learn":[0.04999683245],"iteration":94,"passed_time":15.39314641,"remaining_time":146.6399737},
{"learn":[0.04914290421],"iteration":95,"passed_time":15.55109875,"remaining_time":146.4395132},
{"learn":[0.04851780731],"iteration":96,"passed_time":15.74204069,"remaining_time":146.5470386},
{"learn":[0.04824277099],"iteration":97,"passed_time":15.88656514,"remaining_time":146.2212424},
{"learn":[0.04788311369],"iteration":98,"passed_time":16.03242783,"remaining_time":145.9112876},
{"learn":[0.0476114484],"iteration":99,"passed_time":16.1833471,"remaining_time":145.6501239},
{"learn":[0.04733578748],"iteration":100,"passed_time":16.35233688,"remaining_time":145.5519886},
{"learn":[0.04707158894],"iteration":101,"passed_time":16.52867725,"remaining_time":145.5171781},
{"learn":[0.04653835159],"iteration":102,"passed_time":16.66892394,"remaining_time":145.1652891},
{"learn":[0.04616749155],"iteration":103,"passed_time":16.81932827,"remaining_time":144.904982},
{"learn":[0.04599678402],"iteration":104,"passed_time":16.95164614,"remaining_time":144.4926029},
{"learn":[0.04576649354],"iteration":105,"passed_time":17.08751947,"remaining_time":144.1154944},
{"learn":[0.04556501583],"iteration":106,"passed_time":17.22851145,"remaining_time":143.7856143},
{"learn":[0.04530750889],"iteration":107,"passed_time":17.37167141,"remaining_time":143.477138},
{"learn":[0.04515622018],"iteration":108,"passed_time":17.50571349,"remaining_time":143.0971626},
{"learn":[0.04474425004],"iteration":109,"passed_time":17.66629163,"remaining_time":142.9363595},
{"learn":[0.0445702355],"iteration":110,"passed_time":17.80263338,"remaining_time":142.5814511},
{"learn":[0.0443020222],"iteration":111,"passed_time":17.9463382,"remaining_time":142.2888243},
{"learn":[0.04393389722],"iteration":112,"passed_time":18.10149763,"remaining_time":142.0887468},
{"learn":[0.04382759045],"iteration":113,"passed_time":18.22987774,"remaining_time":141.6813305},
{"learn":[0.04375413532],"iteration":114,"passed_time":18.35966097,"remaining_time":141.2895649},
{"learn":[0.04367965318],"iteration":115,"passed_time":18.48131621,"remaining_time":140.8403752},
{"learn":[0.04349486717],"iteration":116,"passed_time":18.62503132,"remaining_time":140.5632706},
{"learn":[0.0432088353],"iteration":117,"passed_time":18.77298407,"remaining_time":140.3201013},
{"learn":[0.04285682731],"iteration":118,"passed_time":18.92130687,"remaining_time":140.0812719},
{"learn":[0.04266383138],"iteration":119,"passed_time":19.07425847,"remaining_time":139.8778955},
{"learn":[0.04223074662],"iteration":120,"passed_time":19.24064509,"remaining_time":139.7729507},
{"learn":[0.04191956902],"iteration":121,"passed_time":19.39013125,"remaining_time":139.5453708},
{"learn":[0.0417044465],"iteration":122,"passed_time":19.5374985,"remaining_time":139.3039527},
{"learn":[0.04160112358],"iteration":123,"passed_time":19.67336143,"remaining_time":138.9827792},
{"learn":[0.04147307492],"iteration":124,"passed_time":19.81352053,"remaining_time":138.6946437},
{"learn":[0.04128066645],"iteration":125,"passed_time":19.95887999,"remaining_time":138.4449294},
{"learn":[0.04073033543],"iteration":126,"passed_time":20.12274865,"remaining_time":138.3240911},
{"learn":[0.04066903994],"iteration":127,"passed_time":20.24786818,"remaining_time":137.938602},
{"learn":[0.04058918779],"iteration":128,"passed_time":20.37279376,"remaining_time":137.5558401},
{"learn":[0.04032528932],"iteration":129,"passed_time":20.51354076,"remaining_time":137.2829266},
{"learn":[0.04012620093],"iteration":130,"passed_time":20.64800215,"remaining_time":136.9703349},
{"learn":[0.0398203545],"iteration":131,"passed_time":20.79636688,"remaining_time":136.7518671},
{"learn":[0.03973129489],"iteration":132,"passed_time":20.92165707,"remaining_time":136.3840352},
{"learn":[0.03952583674],"iteration":133,"passed_time":21.07391075,"remaining_time":136.1940799},
{"learn":[0.03935236202],"iteration":134,"passed_time":21.22134236,"remaining_time":135.9737862},
{"learn":[0.0391705012],"iteration":135,"passed_time":21.3644544,"remaining_time":135.7271221},
{"learn":[0.03915713533],"iteration":136,"passed_time":21.48799771,"remaining_time":135.3587009},
{"learn":[0.03911643179],"iteration":137,"passed_time":21.61333855,"remaining_time":135.0050567},
{"learn":[0.03900731221],"iteration":138,"passed_time":21.74670272,"remaining_time":134.704396},
{"learn":[0.03863742179],"iteration":139,"passed_time":21.90057266,"remaining_time":134.5320892},
{"learn":[0.03853696692],"iteration":140,"passed_time":22.03490408,"remaining_time":134.2410114},
{"learn":[0.03838953035],"iteration":141,"passed_time":22.1661384,"remaining_time":133.9334278},
{"learn":[0.03833382286],"iteration":142,"passed_time":22.29953054,"remaining_time":133.6412425},
{"learn":[0.03826407422],"iteration":143,"passed_time":22.43871492,"remaining_time":133.3856942},
{"learn":[0.0381615551],"iteration":144,"passed_time":22.5655518,"remaining_time":133.0589434},
{"learn":[0.03795685692],"iteration":145,"passed_time":22.71295551,"remaining_time":132.8552329},
{"learn":[0.03773450796],"iteration":146,"passed_time":22.86750215,"remaining_time":132.6937369},
{"learn":[0.03759844205],"iteration":147,"passed_time":23.01266437,"remaining_time":132.4783111},
{"learn":[0.03726116247],"iteration":148,"passed_time":23.16496628,"remaining_time":132.304606},
{"learn":[0.0371182457],"iteration":149,"passed_time":23.30575537,"remaining_time":132.0659471},
{"learn":[0.03702234528],"iteration":150,"passed_time":23.45108097,"remaining_time":131.854091},
{"learn":[0.03686701692],"iteration":151,"passed_time":23.59826566,"remaining_time":131.6534821},
{"learn":[0.0364420941],"iteration":152,"passed_time":23.75986995,"remaining_time":131.5333977},
{"learn":[0.03634741986],"iteration":153,"passed_time":23.89731634,"remaining_time":131.2800625},
{"learn":[0.03599950583],"iteration":154,"passed_time":24.0429647,"remaining_time":131.0729366},
{"learn":[0.03580382809],"iteration":155,"passed_time":24.18866832,"remaining_time":130.8668978},
{"learn":[0.03562042483],"iteration":156,"passed_time":24.33493672,"remaining_time":130.6646602},
{"learn":[0.03547956321],"iteration":157,"passed_time":24.48239097,"remaining_time":130.4694506},
{"learn":[0.03538467486],"iteration":158,"passed_time":24.62721136,"remaining_time":130.2609104},
{"learn":[0.03526145694],"iteration":159,"passed_time":24.76840157,"remaining_time":130.0341083},
{"learn":[0.03510405764],"iteration":160,"passed_time":24.90976306,"remaining_time":129.8092621},
{"learn":[0.03491191316],"iteration":161,"passed_time":25.05893702,"remaining_time":129.6258594},
{"learn":[0.03474216174],"iteration":162,"passed_time":25.20606057,"remaining_time":129.4323478},
{"learn":[0.03461288455],"iteration":163,"passed_time":25.34208918,"remaining_time":129.1828449},
{"learn":[0.03448157272],"iteration":164,"passed_time":25.4768848,"remaining_time":128.9284776},
{"learn":[0.03426152946],"iteration":165,"passed_time":25.63730297,"remaining_time":128.8042812},
{"learn":[0.03419340849],"iteration":166,"passed_time":25.76063273,"remaining_time":128.4946531},
{"learn":[0.03403187516],"iteration":167,"passed_time":25.9054249,"remaining_time":128.2935328},
{"learn":[0.0339529435],"iteration":168,"passed_time":26.03965394,"remaining_time":128.0411386},
{"learn":[0.03377871146],"iteration":169,"passed_time":26.19309199,"remaining_time":127.8839197},
{"learn":[0.03356442994],"iteration":170,"passed_time":26.35866317,"remaining_time":127.7855659},
{"learn":[0.03340574097],"iteration":171,"passed_time":26.48971455,"remaining_time":127.5202538},
{"learn":[0.03329477386],"iteration":172,"passed_time":26.62099125,"remaining_time":127.2575709},
{"learn":[0.03305840762],"iteration":173,"passed_time":26.76734149,"remaining_time":127.0679544},
{"learn":[0.03297659677],"iteration":174,"passed_time":26.89709804,"remaining_time":126.800605},
{"learn":[0.03287126952],"iteration":175,"passed_time":27.03157745,"remaining_time":126.5569308},
{"learn":[0.03269243411],"iteration":176,"passed_time":27.20223423,"remaining_time":126.4827049},
{"learn":[0.03265529927],"iteration":177,"passed_time":27.33064378,"remaining_time":126.2122988},
{"learn":[0.03255856504],"iteration":178,"passed_time":27.46439203,"remaining_time":125.9679657},
{"learn":[0.03243678795],"iteration":179,"passed_time":27.59438135,"remaining_time":125.7077373},
{"learn":[0.03234001571],"iteration":180,"passed_time":27.72845121,"remaining_time":125.4674118},
{"learn":[0.0322696511],"iteration":181,"passed_time":27.85861772,"remaining_time":125.2107104},
{"learn":[0.03216971693],"iteration":182,"passed_time":27.98573045,"remaining_time":124.9417583},
{"learn":[0.03202249438],"iteration":183,"passed_time":28.13151955,"remaining_time":124.7571737},
{"learn":[0.03166601272],"iteration":184,"passed_time":28.30179486,"remaining_time":124.6808801},
{"learn":[0.03151186201],"iteration":185,"passed_time":28.46060029,"remaining_time":124.5533797},
{"learn":[0.03137843721],"iteration":186,"passed_time":28.60294087,"remaining_time":124.3539622},
{"learn":[0.03115461215],"iteration":187,"passed_time":28.75040022,"remaining_time":124.1772605},
{"learn":[0.0309838958],"iteration":188,"passed_time":28.91101797,"remaining_time":124.0573311},
{"learn":[0.03094198364],"iteration":189,"passed_time":29.03794281,"remaining_time":123.7933351},
{"learn":[0.03089570847],"iteration":190,"passed_time":29.17585113,"remaining_time":123.5772962},
{"learn":[0.03083548371],"iteration":191,"passed_time":29.30827846,"remaining_time":123.3390052},
{"learn":[0.03064321299],"iteration":192,"passed_time":29.46013224,"remaining_time":123.18304},
{"learn":[0.03057164705],"iteration":193,"passed_time":29.58979009,"remaining_time":122.9349011},
{"learn":[0.03052358112],"iteration":194,"passed_time":29.71283724,"remaining_time":122.6606871},
{"learn":[0.03030963242],"iteration":195,"passed_time":29.8775466,"remaining_time":122.5589156},
{"learn":[0.03022553843],"iteration":196,"passed_time":30.00862123,"remaining_time":122.3194053},
{"learn":[0.03017349541],"iteration":197,"passed_time":30.12854886,"remaining_time":122.0358393},
{"learn":[0.03011826377],"iteration":198,"passed_time":30.25812044,"remaining_time":121.7927361},
{"learn":[0.03005305384],"iteration":199,"passed_time":30.38770527,"remaining_time":121.5508211},
{"learn":[0.02998883469],"iteration":200,"passed_time":30.5195834,"remaining_time":121.31914},
{"learn":[0.02983474728],"iteration":201,"passed_time":30.67113751,"remaining_time":121.1661769},
{"learn":[0.02973701238],"iteration":202,"passed_time":30.80237612,"remaining_time":120.9334668},
{"learn":[0.02963467183],"iteration":203,"passed_time":30.94138095,"remaining_time":120.7320551},
{"learn":[0.02950445281],"iteration":204,"passed_time":31.08608598,"remaining_time":120.5533578},
{"learn":[0.02939703078],"iteration":205,"passed_time":31.24280853,"remaining_time":120.4213106},
{"learn":[0.02919083662],"iteration":206,"passed_time":31.39839846,"remaining_time":120.2846859},
{"learn":[0.02908535032],"iteration":207,"passed_time":31.52927655,"remaining_time":120.0537838},
{"learn":[0.02898574603],"iteration":208,"passed_time":31.66774534,"remaining_time":119.8525673},
{"learn":[0.0288661142],"iteration":209,"passed_time":31.80242404,"remaining_time":119.6376904},
{"learn":[0.02875686039],"iteration":210,"passed_time":31.94318666,"remaining_time":119.4463236},
{"learn":[0.02866446933],"iteration":211,"passed_time":32.06988196,"remaining_time":119.2031461},
{"learn":[0.02851445752],"iteration":212,"passed_time":32.22147901,"remaining_time":119.0530703},
{"learn":[0.02840928097],"iteration":213,"passed_time":32.36429159,"remaining_time":118.8707158},
{"learn":[0.02829258121],"iteration":214,"passed_time":32.51170893,"remaining_time":118.7055419},
{"learn":[0.02825152768],"iteration":215,"passed_time":32.63600614,"remaining_time":118.4566149},
{"learn":[0.02812370756],"iteration":216,"passed_time":32.78595989,"remaining_time":118.3014129},
{"learn":[0.02801137234],"iteration":217,"passed_time":32.92385223,"remaining_time":118.1029929},
{"learn":[0.02790312956],"iteration":218,"passed_time":33.06773,"remaining_time":117.9264709},
{"learn":[0.02772899008],"iteration":219,"passed_time":33.21528918,"remaining_time":117.763298},
{"learn":[0.02762262549],"iteration":220,"passed_time":33.35792824,"remaining_time":117.5829235},
{"learn":[0.02755044045],"iteration":221,"passed_time":33.49483698,"remaining_time":117.3828071},
{"learn":[0.02726870618],"iteration":222,"passed_time":33.6549107,"remaining_time":117.2639714},
{"learn":[0.02723628693],"iteration":223,"passed_time":33.77739201,"remaining_time":117.0145366},
{"learn":[0.02717139132],"iteration":224,"passed_time":33.91763946,"remaining_time":116.8274248},
{"learn":[0.02707480838],"iteration":225,"passed_time":34.05295529,"remaining_time":116.623838},
{"learn":[0.02692463277],"iteration":226,"passed_time":34.20298761,"remaining_time":116.4709666},
{"learn":[0.02669681401],"iteration":227,"passed_time":34.3666413,"remaining_time":116.3642416},
{"learn":[0.02651079173],"iteration":228,"passed_time":34.53372248,"remaining_time":116.2685591},
{"learn":[0.02638079257],"iteration":229,"passed_time":34.68246848,"remaining_time":116.1108727},
{"learn":[0.02631484665],"iteration":230,"passed_time":34.80633291,"remaining_time":115.8704329},
{"learn":[0.02615115908],"iteration":231,"passed_time":34.95902732,"remaining_time":115.7264353},
{"learn":[0.02590917794],"iteration":232,"passed_time":35.12108353,"remaining_time":115.6131806},
{"learn":[0.02580160693],"iteration":233,"passed_time":35.27540948,"remaining_time":115.4742037},
{"learn":[0.02572520459],"iteration":234,"passed_time":35.40448815,"remaining_time":115.2529082},
{"learn":[0.02558345131],"iteration":235,"passed_time":35.54687902,"remaining_time":115.0754897},
{"learn":[0.02543381083],"iteration":236,"passed_time":35.69950297,"remaining_time":114.9313113},
{"learn":[0.02536899888],"iteration":237,"passed_time":35.84036202,"remaining_time":114.7493944},
{"learn":[0.02524817893],"iteration":238,"passed_time":35.97226432,"remaining_time":114.5393019},
{"learn":[0.02515261892],"iteration":239,"passed_time":36.1120506,"remaining_time":114.3548269},
{"learn":[0.02505370022],"iteration":240,"passed_time":36.25569224,"remaining_time":114.1828648},
{"learn":[0.02497071132],"iteration":241,"passed_time":36.3999759,"remaining_time":114.0131477},
{"learn":[0.02493375261],"iteration":242,"passed_time":36.52896111,"remaining_time":113.7959817},
{"learn":[0.02479907162],"iteration":243,"passed_time":36.66874062,"remaining_time":113.6129832},
{"learn":[0.02471893167],"iteration":244,"passed_time":36.80656565,"remaining_time":113.4243145},
{"learn":[0.02462559833],"iteration":245,"passed_time":36.94206319,"remaining_time":113.2289254},
{"learn":[0.02452342314],"iteration":246,"passed_time":37.09606779,"remaining_time":113.0904415},
{"learn":[0.02431024231],"iteration":247,"passed_time":37.25403652,"remaining_time":112.9638527},
{"learn":[0.02421735602],"iteration":248,"passed_time":37.38464649,"remaining_time":112.754496},
{"learn":[0.02419054981],"iteration":249,"passed_time":37.51449661,"remaining_time":112.5434898},
{"learn":[0.02416280406],"iteration":250,"passed_time":37.64767809,"remaining_time":112.3430713},
{"learn":[0.02405773165],"iteration":251,"passed_time":37.78557342,"remaining_time":112.1571782},
{"learn":[0.02401855765],"iteration":252,"passed_time":37.92095925,"remaining_time":111.9642552},
{"learn":[0.0238837267],"iteration":253,"passed_time":38.0546599,"remaining_time":111.7668358},
{"learn":[0.02383903678],"iteration":254,"passed_time":38.19675501,"remaining_time":111.5944411},
{"learn":[0.02372228288],"iteration":255,"passed_time":38.3364769,"remaining_time":111.415386},
{"learn":[0.02367199195],"iteration":256,"passed_time":38.47231504,"remaining_time":111.2254088},
{"learn":[0.02359335814],"iteration":257,"passed_time":38.61504679,"remaining_time":111.0556772},
{"learn":[0.02352195271],"iteration":258,"passed_time":38.7591839,"remaining_time":110.8901748},
{"learn":[0.02345192373],"iteration":259,"passed_time":38.90271629,"remaining_time":110.7231156},
{"learn":[0.02338576926],"iteration":260,"passed_time":39.03864883,"remaining_time":110.5347183},
{"learn":[0.02327881491],"iteration":261,"passed_time":39.18337715,"remaining_time":110.3714975},
{"learn":[0.02319559435],"iteration":262,"passed_time":39.33748323,"remaining_time":110.2346964},
{"learn":[0.02304124919],"iteration":263,"passed_time":39.4802065,"remaining_time":110.0660303},
{"learn":[0.02300488764],"iteration":264,"passed_time":39.61123619,"remaining_time":109.8651268},
{"learn":[0.02287639699],"iteration":265,"passed_time":39.76862581,"remaining_time":109.7374863},
{"learn":[0.02277332784],"iteration":266,"passed_time":39.91168724,"remaining_time":109.5702874},
{"learn":[0.02275420408],"iteration":267,"passed_time":40.04003932,"remaining_time":109.3630925},
{"learn":[0.02272805619],"iteration":268,"passed_time":40.16694715,"remaining_time":109.152559},
{"learn":[0.02259318342],"iteration":269,"passed_time":40.3280846,"remaining_time":109.0351917},
{"learn":[0.02255798668],"iteration":270,"passed_time":40.47603514,"remaining_time":108.8820281},
{"learn":[0.02246254679],"iteration":271,"passed_time":40.62630051,"remaining_time":108.7350984},
{"learn":[0.02240587695],"iteration":272,"passed_time":40.76830345,"remaining_time":108.5661414},
{"learn":[0.02235915547],"iteration":273,"passed_time":40.89830365,"remaining_time":108.3655783},
{"learn":[0.02226825297],"iteration":274,"passed_time":41.05373672,"remaining_time":108.2325786},
{"learn":[0.02224139669],"iteration":275,"passed_time":41.18117769,"remaining_time":108.0259878},
{"learn":[0.02219877825],"iteration":276,"passed_time":41.31642268,"remaining_time":107.8403379},
{"learn":[0.0221202207],"iteration":277,"passed_time":41.45437975,"remaining_time":107.6620942},
{"learn":[0.02198021729],"iteration":278,"passed_time":41.61574779,"remaining_time":107.5446386},
{"learn":[0.02187786208],"iteration":279,"passed_time":41.77563557,"remaining_time":107.4230629},
{"learn":[0.02180717503],"iteration":280,"passed_time":41.91971453,"remaining_time":107.2607642},
{"learn":[0.02175156806],"iteration":281,"passed_time":42.06219746,"remaining_time":107.0945311},
{"learn":[0.02168710976],"iteration":282,"passed_time":42.20281467,"remaining_time":106.9237389},
{"learn":[0.02158143279],"iteration":283,"passed_time":42.33121583,"remaining_time":106.722361},
{"learn":[0.02151480901],"iteration":284,"passed_time":42.45952715,"remaining_time":106.5212699},
{"learn":[0.02141576691],"iteration":285,"passed_time":42.61270144,"remaining_time":106.3827581},
{"learn":[0.02136099633],"iteration":286,"passed_time":42.7456759,"remaining_time":106.1939614},
{"learn":[0.02121763041],"iteration":287,"passed_time":42.90786125,"remaining_time":106.0777681},
{"learn":[0.02106344397],"iteration":288,"passed_time":43.06266812,"remaining_time":105.9431039},
{"learn":[0.02101472268],"iteration":289,"passed_time":43.2024981,"remaining_time":105.7716333},
{"learn":[0.02091315318],"iteration":290,"passed_time":43.34927967,"remaining_time":105.6173171},
{"learn":[0.02088432975],"iteration":291,"passed_time":43.49122621,"remaining_time":105.4513293},
{"learn":[0.02083039244],"iteration":292,"passed_time":43.62894734,"remaining_time":105.2753098},
{"learn":[0.02078317952],"iteration":293,"passed_time":43.77002816,"remaining_time":105.1076186},
{"learn":[0.02070694074],"iteration":294,"passed_time":43.91055492,"remaining_time":104.9387838},
{"learn":[0.02062510386],"iteration":295,"passed_time":44.05760102,"remaining_time":104.7856457},
{"learn":[0.02055190074],"iteration":296,"passed_time":44.21629562,"remaining_time":104.6601206},
{"learn":[0.02049675277],"iteration":297,"passed_time":44.35588189,"remaining_time":104.4893594},
{"learn":[0.0203932071],"iteration":298,"passed_time":44.50520635,"remaining_time":104.3416376},
{"learn":[0.02035826751],"iteration":299,"passed_time":44.63960521,"remaining_time":104.1590788},
{"learn":[0.02030907326],"iteration":300,"passed_time":44.77730136,"remaining_time":103.9844972},
{"learn":[0.02028221394],"iteration":301,"passed_time":44.91305084,"remaining_time":103.8056606},
{"learn":[0.02024148119],"iteration":302,"passed_time":45.04772486,"remaining_time":103.6246344},
{"learn":[0.0201839366],"iteration":303,"passed_time":45.19345911,"remaining_time":103.4692353},
{"learn":[0.02011115501],"iteration":304,"passed_time":45.34443774,"remaining_time":103.3258499},
{"learn":[0.02010242399],"iteration":305,"passed_time":45.47912407,"remaining_time":103.1454644},
{"learn":[0.02004082799],"iteration":306,"passed_time":45.62211114,"remaining_time":102.9841141},
{"learn":[0.02001542702],"iteration":307,"passed_time":45.75726206,"remaining_time":102.8052771},
{"learn":[0.0199511458],"iteration":308,"passed_time":45.90944753,"remaining_time":102.6648163},
{"learn":[0.01986498889],"iteration":309,"passed_time":46.05038743,"remaining_time":102.4992494},
{"learn":[0.01983597944],"iteration":310,"passed_time":46.18073206,"remaining_time":102.3103678},
{"learn":[0.01975061112],"iteration":311,"passed_time":46.32993006,"remaining_time":102.1634355},
{"learn":[0.019664139],"iteration":312,"passed_time":46.48429795,"remaining_time":102.0278361},
{"learn":[0.01941430152],"iteration":313,"passed_time":46.65437687,"remaining_time":101.9264412},
{"learn":[0.01922700291],"iteration":314,"passed_time":46.82302211,"remaining_time":101.8214925},
{"learn":[0.01921226584],"iteration":315,"passed_time":46.96365566,"remaining_time":101.6555078},
{"learn":[0.0191435429],"iteration":316,"passed_time":47.10128576,"remaining_time":101.4832119},
{"learn":[0.01901591293],"iteration":317,"passed_time":47.26658753,"remaining_time":101.3704802},
{"learn":[0.01901190841],"iteration":318,"passed_time":47.38996485,"remaining_time":101.1679187},
{"learn":[0.01896100866],"iteration":319,"passed_time":47.52827406,"remaining_time":100.9975824},
{"learn":[0.01890638043],"iteration":320,"passed_time":47.67448598,"remaining_time":100.8441619},
{"learn":[0.0188490733],"iteration":321,"passed_time":47.82295612,"remaining_time":100.6955411},
{"learn":[0.01884139872],"iteration":322,"passed_time":47.95938071,"remaining_time":100.5216741},
{"learn":[0.01879314738],"iteration":323,"passed_time":48.08639877,"remaining_time":100.3284122},
{"learn":[0.01873550583],"iteration":324,"passed_time":48.20817581,"remaining_time":100.1246728},
{"learn":[0.01870685772],"iteration":325,"passed_time":48.3480999,"remaining_time":99.95895501},
{"learn":[0.01868164998],"iteration":326,"passed_time":48.47284875,"remaining_time":99.76216271},
{"learn":[0.01862143641],"iteration":327,"passed_time":48.60375148,"remaining_time":99.57841767},
{"learn":[0.01857552654],"iteration":328,"passed_time":48.74706451,"remaining_time":99.42030482},
{"learn":[0.01846902202],"iteration":329,"passed_time":48.89936748,"remaining_time":99.28053397},
{"learn":[0.01839250984],"iteration":330,"passed_time":49.04707434,"remaining_time":99.13139798},
{"learn":[0.01836678104],"iteration":331,"passed_time":49.18401073,"remaining_time":98.9605999},
{"learn":[0.01831568704],"iteration":332,"passed_time":49.32885062,"remaining_time":98.80583593},
{"learn":[0.01824912246],"iteration":333,"passed_time":49.48299942,"remaining_time":98.66969346},
{"learn":[0.01819186972],"iteration":334,"passed_time":49.63565798,"remaining_time":98.53048524},
{"learn":[0.01808473137],"iteration":335,"passed_time":49.78592087,"remaining_time":98.38646267},
{"learn":[0.01805649824],"iteration":336,"passed_time":49.91140131,"remaining_time":98.19364709},
{"learn":[0.01798226751],"iteration":337,"passed_time":50.05243115,"remaining_time":98.03168468},
{"learn":[0.0179253786],"iteration":338,"passed_time":50.19022939,"remaining_time":97.86354462},
{"learn":[0.01775383151],"iteration":339,"passed_time":50.32643671,"remaining_time":97.69249479},
{"learn":[0.01768856397],"iteration":340,"passed_time":50.47060668,"remaining_time":97.53703755},
{"learn":[0.01765955827],"iteration":341,"passed_time":50.60857539,"remaining_time":97.36971522},
{"learn":[0.01765269044],"iteration":342,"passed_time":50.74062413,"remaining_time":97.19122465},
{"learn":[0.01758473174],"iteration":343,"passed_time":50.8983457,"remaining_time":97.06196157},
{"learn":[0.01754651059],"iteration":344,"passed_time":51.03932287,"remaining_time":96.90074341},
{"learn":[0.01751765168],"iteration":345,"passed_time":51.17721241,"remaining_time":96.73380612},
{"learn":[0.0174639292],"iteration":346,"passed_time":51.32190458,"remaining_time":96.57983772},
{"learn":[0.01743191783],"iteration":347,"passed_time":51.4597012,"remaining_time":96.4130034},
{"learn":[0.0173952523],"iteration":348,"passed_time":51.59769667,"remaining_time":96.2467064},
{"learn":[0.01735541236],"iteration":349,"passed_time":51.73923018,"remaining_time":96.08714177},
{"learn":[0.01730575285],"iteration":350,"passed_time":51.87387098,"remaining_time":95.91493523},
{"learn":[0.01728333724],"iteration":351,"passed_time":52.00450011,"remaining_time":95.73555702},
{"learn":[0.01724284341],"iteration":352,"passed_time":52.14586406,"remaining_time":95.57613045},
{"learn":[0.01721242973],"iteration":353,"passed_time":52.27787696,"remaining_time":95.39974158},
{"learn":[0.01713825678],"iteration":354,"passed_time":52.41706623,"remaining_time":95.23664146},
{"learn":[0.01712445214],"iteration":355,"passed_time":52.53660665,"remaining_time":95.03813113},
{"learn":[0.01708285669],"iteration":356,"passed_time":52.68230515,"remaining_time":94.88717706},
{"learn":[0.01706145649],"iteration":357,"passed_time":52.81846604,"remaining_time":94.7191486},
{"learn":[0.01699355603],"iteration":358,"passed_time":52.95935603,"remaining_time":94.55974155},
{"learn":[0.01697161232],"iteration":359,"passed_time":53.09613103,"remaining_time":94.39312184},
{"learn":[0.01696567544],"iteration":360,"passed_time":53.23156324,"remaining_time":94.22429061},
{"learn":[0.01691302947],"iteration":361,"passed_time":53.38377895,"remaining_time":94.08522368},
{"learn":[0.01685235163],"iteration":362,"passed_time":53.55232117,"remaining_time":93.9747344},
{"learn":[0.01679135456],"iteration":363,"passed_time":53.69127636,"remaining_time":93.81223012},
{"learn":[0.01673368009],"iteration":364,"passed_time":53.83110759,"remaining_time":93.65137896},
{"learn":[0.01671952672],"iteration":365,"passed_time":53.9666381,"remaining_time":93.48319277},
{"learn":[0.01665994123],"iteration":366,"passed_time":54.10699849,"remaining_time":93.32351511},
{"learn":[0.01659290456],"iteration":367,"passed_time":54.24568966,"remaining_time":93.16107572},
{"learn":[0.01656751085],"iteration":368,"passed_time":54.38786826,"remaining_time":93.00472866},
{"learn":[0.01651496092],"iteration":369,"passed_time":54.53692606,"remaining_time":92.8601714},
{"learn":[0.01646752574],"iteration":370,"passed_time":54.67816099,"remaining_time":92.70232685},
{"learn":[0.01639834664],"iteration":371,"passed_time":54.83712302,"remaining_time":92.574498},
{"learn":[0.01627209579],"iteration":372,"passed_time":54.97036989,"remaining_time":92.40327593},
{"learn":[0.01622710921],"iteration":373,"passed_time":55.11211498,"remaining_time":92.24648123},
{"learn":[0.01621008985],"iteration":374,"passed_time":55.25383618,"remaining_time":92.08972697},
{"learn":[0.0161989145],"iteration":375,"passed_time":55.38220284,"remaining_time":91.91088983},
{"learn":[0.01615117254],"iteration":376,"passed_time":55.53730673,"remaining_time":91.77650422},
{"learn":[0.01609483118],"iteration":377,"passed_time":55.68915589,"remaining_time":91.63665335},
{"learn":[0.01607395656],"iteration":378,"passed_time":55.83288956,"remaining_time":91.48344173},
{"learn":[0.0160309932],"iteration":379,"passed_time":55.96057305,"remaining_time":91.30409287},
{"learn":[0.01600564678],"iteration":380,"passed_time":56.09255081,"remaining_time":91.131992},
{"learn":[0.01591513725],"iteration":381,"passed_time":56.2523104,"remaining_time":91.00504667},
{"learn":[0.0158460703],"iteration":382,"passed_time":56.40261104,"remaining_time":90.86269194},
{"learn":[0.01575484854],"iteration":383,"passed_time":56.55092574,"remaining_time":90.71711004},
{"learn":[0.01572155526],"iteration":384,"passed_time":56.69895033,"remaining_time":90.57105052},
{"learn":[0.01570080084],"iteration":385,"passed_time":56.83635606,"remaining_time":90.40808968},
{"learn":[0.01569208797],"iteration":386,"passed_time":56.98067842,"remaining_time":90.25621672},
{"learn":[0.01565912331],"iteration":387,"passed_time":57.13085151,"remaining_time":90.11361115},
{"learn":[0.01560329025],"iteration":388,"passed_time":57.26532245,"remaining_time":89.94630339},
{"learn":[0.01558236805],"iteration":389,"passed_time":57.39400726,"remaining_time":89.77011393},
{"learn":[0.0155424675],"iteration":390,"passed_time":57.54181398,"remaining_time":89.62395068},
{"learn":[0.01545229253],"iteration":391,"passed_time":57.69069291,"remaining_time":89.47944206},
{"learn":[0.01541096318],"iteration":392,"passed_time":57.82751056,"remaining_time":89.31628221},
{"learn":[0.01538866501],"iteration":393,"passed_time":57.96420799,"remaining_time":89.15307117},
{"learn":[0.01535133055],"iteration":394,"passed_time":58.10831944,"remaining_time":89.00135003},
{"learn":[0.01531251955],"iteration":395,"passed_time":58.25359284,"remaining_time":88.85143959},
{"learn":[0.01528140355],"iteration":396,"passed_time":58.38164664,"remaining_time":88.67539779},
{"learn":[0.01522776035],"iteration":397,"passed_time":58.52635068,"remaining_time":88.52478168},
{"learn":[0.0152120114],"iteration":398,"passed_time":58.66376674,"remaining_time":88.36321758},
{"learn":[0.01514619006],"iteration":399,"passed_time":58.81320909,"remaining_time":88.21981364},
{"learn":[0.01512989872],"iteration":400,"passed_time":58.93699513,"remaining_time":88.03805507},
{"learn":[0.01510952135],"iteration":401,"passed_time":59.07421145,"remaining_time":87.8765633},
{"learn":[0.01507444739],"iteration":402,"passed_time":59.21823609,"remaining_time":87.72527779},
{"learn":[0.01505712912],"iteration":403,"passed_time":59.35470266,"remaining_time":87.56287819},
{"learn":[0.01498028776],"iteration":404,"passed_time":59.50218058,"remaining_time":87.41678382},
{"learn":[0.01497546895],"iteration":405,"passed_time":59.62802786,"remaining_time":87.23903584},
{"learn":[0.01497538625],"iteration":406,"passed_time":59.7441315,"remaining_time":87.04734639},
{"learn":[0.01497078314],"iteration":407,"passed_time":59.86249758,"remaining_time":86.85931021},
{"learn":[0.01487334866],"iteration":408,"passed_time":59.99512064,"remaining_time":86.69221589},
{"learn":[0.01482643603],"iteration":409,"passed_time":60.13770863,"remaining_time":86.53962949},
{"learn":[0.01480261241],"iteration":410,"passed_time":60.27053732,"remaining_time":86.37310579},
{"learn":[0.01475281329],"iteration":411,"passed_time":60.41993069,"remaining_time":86.23038651},
{"learn":[0.01473946211],"iteration":412,"passed_time":60.54767845,"remaining_time":86.05686985},
{"learn":[0.01473945124],"iteration":413,"passed_time":60.67566223,"remaining_time":85.88390837},
{"learn":[0.01470077643],"iteration":414,"passed_time":60.83413696,"remaining_time":85.75414488},
{"learn":[0.01465735375],"iteration":415,"passed_time":60.99756452,"remaining_time":85.63119635},
{"learn":[0.01462860635],"iteration":416,"passed_time":61.12931159,"remaining_time":85.46376177},
{"learn":[0.01458271914],"iteration":417,"passed_time":61.26434826,"remaining_time":85.3010782},
{"learn":[0.01457748882],"iteration":418,"passed_time":61.39219515,"remaining_time":85.128557},
{"learn":[0.0145616246],"iteration":419,"passed_time":61.52973396,"remaining_time":84.96963261},
{"learn":[0.01453825048],"iteration":420,"passed_time":61.66510574,"remaining_time":84.80782951},
{"learn":[0.01453823279],"iteration":421,"passed_time":61.79527093,"remaining_time":84.63902038},
{"learn":[0.01451823695],"iteration":422,"passed_time":61.92941373,"remaining_time":84.47581968},
{"learn":[0.0145017473],"iteration":423,"passed_time":62.05265121,"remaining_time":84.29794126},
{"learn":[0.01447730608],"iteration":424,"passed_time":62.18617591,"remaining_time":84.13423799},
{"learn":[0.01444009617],"iteration":425,"passed_time":62.33797989,"remaining_time":83.99530624},
{"learn":[0.01440569016],"iteration":426,"passed_time":62.46847648,"remaining_time":83.82772137},
{"learn":[0.01435975528],"iteration":427,"passed_time":62.6066628,"remaining_time":83.67058673},
{"learn":[0.01431611591],"iteration":428,"passed_time":62.74633152,"remaining_time":83.51551351},
{"learn":[0.01424905828],"iteration":429,"passed_time":62.90251116,"remaining_time":83.38239851},
{"learn":[0.01423545754],"iteration":430,"passed_time":63.0240631,"remaining_time":83.20346149},
{"learn":[0.01420741664],"iteration":431,"passed_time":63.17177674,"remaining_time":83.05918793},
{"learn":[0.01418188661],"iteration":432,"passed_time":63.30287321,"remaining_time":82.89313882},
{"learn":[0.01415902486],"iteration":433,"passed_time":63.43214237,"remaining_time":82.7248677},
{"learn":[0.014136895],"iteration":434,"passed_time":63.57829663,"remaining_time":82.57870712},
{"learn":[0.0140392498],"iteration":435,"passed_time":63.71247884,"remaining_time":82.41705978},
{"learn":[0.01398221572],"iteration":436,"passed_time":63.85792482,"remaining_time":82.2700496},
{"learn":[0.01396889136],"iteration":437,"passed_time":63.98161368,"remaining_time":82.09512988},
{"learn":[0.01389793268],"iteration":438,"passed_time":64.14299863,"remaining_time":81.96861556},
{"learn":[0.01381068205],"iteration":439,"passed_time":64.29164206,"remaining_time":81.82572626},
{"learn":[0.01379255579],"iteration":440,"passed_time":64.41864903,"remaining_time":81.65538505},
{"learn":[0.01377498992],"iteration":441,"passed_time":64.55666665,"remaining_time":81.49914025},
{"learn":[0.01375396898],"iteration":442,"passed_time":64.68612905,"remaining_time":81.33222095},
{"learn":[0.01373119896],"iteration":443,"passed_time":64.82825159,"remaining_time":81.18132406},
{"learn":[0.01372408182],"iteration":444,"passed_time":64.96231318,"remaining_time":81.02041307},
{"learn":[0.01371794758],"iteration":445,"passed_time":65.09756003,"remaining_time":80.86109475},
{"learn":[0.01367737511],"iteration":446,"passed_time":65.23951196,"remaining_time":80.71017922},
{"learn":[0.0136504002],"iteration":447,"passed_time":65.37179594,"remaining_time":80.54739143},
{"learn":[0.01363672945],"iteration":448,"passed_time":65.52066946,"remaining_time":80.40509771},
{"learn":[0.01362317046],"iteration":449,"passed_time":65.64174164,"remaining_time":80.22879533},
{"learn":[0.01360164522],"iteration":450,"passed_time":65.78376982,"remaining_time":80.07824752},
{"learn":[0.01354880334],"iteration":451,"passed_time":65.92619445,"remaining_time":79.92821805},
{"learn":[0.01347521867],"iteration":452,"passed_time":66.07723698,"remaining_time":79.78862831},
{"learn":[0.01344399606],"iteration":453,"passed_time":66.2140063,"remaining_time":79.63182255},
{"learn":[0.01339189123],"iteration":454,"passed_time":66.36350366,"remaining_time":79.49035054},
{"learn":[0.01338538883],"iteration":455,"passed_time":66.50423725,"remaining_time":79.3383883},
{"learn":[0.01332384295],"iteration":456,"passed_time":66.65726124,"remaining_time":79.20107845},
{"learn":[0.0132948833],"iteration":457,"passed_time":66.79080806,"remaining_time":79.04065059},
{"learn":[0.01324697691],"iteration":458,"passed_time":66.9190511,"remaining_time":78.87408856},
{"learn":[0.01321738921],"iteration":459,"passed_time":67.07309411,"remaining_time":78.73798005},
{"learn":[0.01317022348],"iteration":460,"passed_time":67.21164763,"remaining_time":78.58368346},
{"learn":[0.01313657267],"iteration":461,"passed_time":67.35616384,"remaining_time":78.43639859},
{"learn":[0.01310784624],"iteration":462,"passed_time":67.47668319,"remaining_time":78.26129347},
{"learn":[0.0130919139],"iteration":463,"passed_time":67.60697109,"remaining_time":78.09770799},
{"learn":[0.01306936414],"iteration":464,"passed_time":67.73740153,"remaining_time":77.93442971},
{"learn":[0.01301404079],"iteration":465,"passed_time":67.88581241,"remaining_time":77.79189663},
{"learn":[0.01298560085],"iteration":466,"passed_time":68.01576975,"remaining_time":77.62827683},
{"learn":[0.01292421416],"iteration":467,"passed_time":68.17738689,"remaining_time":77.50079023},
{"learn":[0.01291568137],"iteration":468,"passed_time":68.30995176,"remaining_time":77.34026521},
{"learn":[0.01289967222],"iteration":469,"passed_time":68.44068209,"remaining_time":77.17779045},
{"learn":[0.01289127635],"iteration":470,"passed_time":68.58431494,"remaining_time":77.02994183},
{"learn":[0.01286460359],"iteration":471,"passed_time":68.71866268,"remaining_time":76.87172435},
{"learn":[0.01282974656],"iteration":472,"passed_time":68.85303525,"remaining_time":76.71363547},
{"learn":[0.01281613183],"iteration":473,"passed_time":68.98039416,"remaining_time":76.54786356},
{"learn":[0.01280504954],"iteration":474,"passed_time":69.12215076,"remaining_time":76.39816663},
{"learn":[0.01273525847],"iteration":475,"passed_time":69.2719568,"remaining_time":76.25736421},
{"learn":[0.01272685182],"iteration":476,"passed_time":69.40316943,"remaining_time":76.09613755},
{"learn":[0.0126895384],"iteration":477,"passed_time":69.55276497,"remaining_time":75.95511154},
{"learn":[0.0126761282],"iteration":478,"passed_time":69.68338848,"remaining_time":75.79341419},
{"learn":[0.01261899193],"iteration":479,"passed_time":69.82778243,"remaining_time":75.6467643},
{"learn":[0.01257531143],"iteration":480,"passed_time":69.96885593,"remaining_time":75.49654101},
{"learn":[0.01256655689],"iteration":481,"passed_time":70.09252954,"remaining_time":75.32765623},
{"learn":[0.01256652124],"iteration":482,"passed_time":70.21579335,"remaining_time":75.15852001},
{"learn":[0.01255869971],"iteration":483,"passed_time":70.34029762,"remaining_time":74.99089581},
{"learn":[0.01255555859],"iteration":484,"passed_time":70.45475552,"remaining_time":74.81278164},
{"learn":[0.01255554578],"iteration":485,"passed_time":70.57958235,"remaining_time":74.64589574},
{"learn":[0.01254206092],"iteration":486,"passed_time":70.71305106,"remaining_time":74.48828582},
{"learn":[0.01252817392],"iteration":487,"passed_time":70.85215652,"remaining_time":74.33668881},
{"learn":[0.01252817392],"iteration":488,"passed_time":70.98230835,"remaining_time":74.17578644},
{"learn":[0.01251444428],"iteration":489,"passed_time":71.10643356,"remaining_time":74.00873697},
{"learn":[0.01250021886],"iteration":490,"passed_time":71.46303979,"remaining_time":74.0828661},
{"learn":[0.01249879535],"iteration":491,"passed_time":71.58620008,"remaining_time":73.91420658},
{"learn":[0.01243576107],"iteration":492,"passed_time":71.73934662,"remaining_time":73.77656944},
{"learn":[0.01233982328],"iteration":493,"passed_time":71.90072372,"remaining_time":73.64730001},
{"learn":[0.01232733824],"iteration":494,"passed_time":72.03106501,"remaining_time":73.48623804},
{"learn":[0.01230842528],"iteration":495,"passed_time":72.15992091,"remaining_time":73.3237906},
{"learn":[0.01228258873],"iteration":496,"passed_time":72.29711238,"remaining_time":73.16991454},
{"learn":[0.01226975955],"iteration":497,"passed_time":72.4209265,"remaining_time":73.00262069},
{"learn":[0.01221872608],"iteration":498,"passed_time":72.56255478,"remaining_time":72.85338667},
{"learn":[0.01220246991],"iteration":499,"passed_time":72.69900159,"remaining_time":72.69900159},
{"learn":[0.01216301554],"iteration":500,"passed_time":72.84006525,"remaining_time":72.54928655},
{"learn":[0.01203814778],"iteration":501,"passed_time":72.98559428,"remaining_time":72.40403576},
{"learn":[0.01201015571],"iteration":502,"passed_time":73.12128435,"remaining_time":72.24906227},
{"learn":[0.01197875712],"iteration":503,"passed_time":73.25742564,"remaining_time":72.09460936},
{"learn":[0.01196874233],"iteration":504,"passed_time":73.39816129,"remaining_time":71.94473235},
{"learn":[0.0119687423],"iteration":505,"passed_time":73.51545297,"remaining_time":71.7720035},
{"learn":[0.01196476516],"iteration":506,"passed_time":73.63420494,"remaining_time":71.60091328},
{"learn":[0.01193548185],"iteration":507,"passed_time":73.76259177,"remaining_time":71.43936053},
{"learn":[0.01190681324],"iteration":508,"passed_time":73.89621699,"remaining_time":71.28299124},
{"learn":[0.01189292207],"iteration":509,"passed_time":74.01548549,"remaining_time":71.11291743},
{"learn":[0.0118929049],"iteration":510,"passed_time":74.14000436,"remaining_time":70.94806679},
{"learn":[0.01187633554],"iteration":511,"passed_time":74.26826793,"remaining_time":70.78694287},
{"learn":[0.01187053891],"iteration":512,"passed_time":74.38786792,"remaining_time":70.61772257},
{"learn":[0.01185980874],"iteration":513,"passed_time":74.53181837,"remaining_time":70.47171931},
{"learn":[0.01181657162],"iteration":514,"passed_time":74.67754364,"remaining_time":70.32739547},
{"learn":[0.01178534043],"iteration":515,"passed_time":74.82907084,"remaining_time":70.18850831},
{"learn":[0.01177791448],"iteration":516,"passed_time":74.96663046,"remaining_time":70.03652323},
{"learn":[0.01177351439],"iteration":517,"passed_time":75.08657191,"remaining_time":69.86820012},
{"learn":[0.0117734997],"iteration":518,"passed_time":75.20386455,"remaining_time":69.69760857},
{"learn":[0.01176268199],"iteration":519,"passed_time":75.33745537,"remaining_time":69.54226649},
{"learn":[0.0117626703],"iteration":520,"passed_time":75.46804191,"remaining_time":69.38424583},
{"learn":[0.0117626458],"iteration":521,"passed_time":75.58258062,"remaining_time":69.21163513},
{"learn":[0.01175472069],"iteration":522,"passed_time":75.71276841,"remaining_time":69.05351918},
{"learn":[0.01173307594],"iteration":523,"passed_time":75.8552294,"remaining_time":68.90665877},
{"learn":[0.01167935704],"iteration":524,"passed_time":76.01282785,"remaining_time":68.77351092},
{"learn":[0.01167242286],"iteration":525,"passed_time":76.13927237,"remaining_time":68.61219602},
{"learn":[0.01165136002],"iteration":526,"passed_time":76.27887173,"remaining_time":68.46282036},
{"learn":[0.0116387668],"iteration":527,"passed_time":76.39699552,"remaining_time":68.29428388},
{"learn":[0.01160615013],"iteration":528,"passed_time":76.54700105,"remaining_time":68.15432419},
{"learn":[0.01159711538],"iteration":529,"passed_time":76.68129973,"remaining_time":68.00039788},
{"learn":[0.01159711538],"iteration":530,"passed_time":76.80429735,"remaining_time":67.83656395},
{"learn":[0.0115825474],"iteration":531,"passed_time":76.93148375,"remaining_time":67.67656841},
{"learn":[0.01154461502],"iteration":532,"passed_time":77.08465244,"remaining_time":67.53946096},
{"learn":[0.0115225556],"iteration":533,"passed_time":77.2244198,"remaining_time":67.39059855},
{"learn":[0.01151404139],"iteration":534,"passed_time":77.35859561,"remaining_time":67.23691021},
{"learn":[0.01149223911],"iteration":535,"passed_time":77.49376462,"remaining_time":67.08415444},
{"learn":[0.01144976178],"iteration":536,"passed_time":77.63879929,"remaining_time":66.93997034},
{"learn":[0.0114191179],"iteration":537,"passed_time":77.79756502,"remaining_time":66.80757443},
{"learn":[0.01138457988],"iteration":538,"passed_time":77.95139988,"remaining_time":66.67086335},
{"learn":[0.01137113486],"iteration":539,"passed_time":78.08340567,"remaining_time":66.51549372},
{"learn":[0.01133376609],"iteration":540,"passed_time":78.23155627,"remaining_time":66.37390818},
{"learn":[0.01132520997],"iteration":541,"passed_time":78.37183832,"remaining_time":66.22564935},
{"learn":[0.01130383479],"iteration":542,"passed_time":78.50366372,"remaining_time":66.07030262},
{"learn":[0.0113038201],"iteration":543,"passed_time":78.62346053,"remaining_time":65.90495957},
{"learn":[0.0112923865],"iteration":544,"passed_time":78.74522432,"remaining_time":65.74142581},
{"learn":[0.01128722598],"iteration":545,"passed_time":78.87101382,"remaining_time":65.58139244},
{"learn":[0.01128517661],"iteration":546,"passed_time":78.99056369,"remaining_time":65.41631692},
{"learn":[0.01127455001],"iteration":547,"passed_time":79.12129841,"remaining_time":65.26063299},
{"learn":[0.01126542238],"iteration":548,"passed_time":79.24580344,"remaining_time":65.09992231},
{"learn":[0.01125464736],"iteration":549,"passed_time":79.37359122,"remaining_time":64.94202918},
{"learn":[0.01124742407],"iteration":550,"passed_time":79.50654447,"remaining_time":64.78845457},
{"learn":[0.01120034921],"iteration":551,"passed_time":79.63958494,"remaining_time":64.63502546},
{"learn":[0.01117134858],"iteration":552,"passed_time":79.77534055,"remaining_time":64.48386479},
{"learn":[0.01112519633],"iteration":553,"passed_time":79.92838361,"remaining_time":64.34667706},
{"learn":[0.01110384699],"iteration":554,"passed_time":80.07116067,"remaining_time":64.20120089},
{"learn":[0.01108641709],"iteration":555,"passed_time":80.21277056,"remaining_time":64.05480239},
{"learn":[0.01106538386],"iteration":556,"passed_time":80.34155236,"remaining_time":63.89821848},
{"learn":[0.0110635013],"iteration":557,"passed_time":80.46653658,"remaining_time":63.73872611},
{"learn":[0.01104094674],"iteration":558,"passed_time":80.61547694,"remaining_time":63.5982564},
{"learn":[0.01101341548],"iteration":559,"passed_time":80.76276817,"remaining_time":63.4564607},
{"learn":[0.01100056845],"iteration":560,"passed_time":80.89287771,"remaining_time":63.30120021},
{"learn":[0.01099175164],"iteration":561,"passed_time":81.0289656,"remaining_time":63.15068849},
{"learn":[0.01096084088],"iteration":562,"passed_time":81.18417156,"remaining_time":63.01506744},
{"learn":[0.01092477803],"iteration":563,"passed_time":81.33164758,"remaining_time":62.87340132},
{"learn":[0.01090684979],"iteration":564,"passed_time":81.4655027,"remaining_time":62.72122774},
{"learn":[0.01088569472],"iteration":565,"passed_time":81.60147458,"remaining_time":62.57074199},
{"learn":[0.01086587891],"iteration":566,"passed_time":81.74187952,"remaining_time":62.42369283},
{"learn":[0.01084172436],"iteration":567,"passed_time":81.88544881,"remaining_time":62.27907375},
{"learn":[0.01080789811],"iteration":568,"passed_time":82.02603374,"remaining_time":62.13219779},
{"learn":[0.01076422897],"iteration":569,"passed_time":82.17447065,"remaining_time":61.99126733},
{"learn":[0.01076106578],"iteration":570,"passed_time":82.29182364,"remaining_time":61.82695682},
{"learn":[0.01073691117],"iteration":571,"passed_time":82.42947278,"remaining_time":61.67799711},
{"learn":[0.01070649619],"iteration":572,"passed_time":82.5775053,"remaining_time":61.5368146},
{"learn":[0.01067917095],"iteration":573,"passed_time":82.7136792,"remaining_time":61.38680721},
{"learn":[0.01066091237],"iteration":574,"passed_time":82.84200812,"remaining_time":61.23104948},
{"learn":[0.01063637593],"iteration":575,"passed_time":82.98778936,"remaining_time":61.08823383},
{"learn":[0.01061623209],"iteration":576,"passed_time":83.1361976,"remaining_time":60.94733377},
{"learn":[0.01059245905],"iteration":577,"passed_time":83.26359259,"remaining_time":60.79106587},
{"learn":[0.01057916177],"iteration":578,"passed_time":83.39704578,"remaining_time":60.63930272},
{"learn":[0.01057192031],"iteration":579,"passed_time":83.52999038,"remaining_time":60.48723441},
{"learn":[0.01055971236],"iteration":580,"passed_time":83.66452835,"remaining_time":60.33638103},
{"learn":[0.01051337428],"iteration":581,"passed_time":83.81597514,"remaining_time":60.19772785},
{"learn":[0.01048479479],"iteration":582,"passed_time":83.96783259,"remaining_time":60.05932451},
{"learn":[0.01041038248],"iteration":583,"passed_time":84.12600593,"remaining_time":59.92537409},
{"learn":[0.01039371345],"iteration":584,"passed_time":84.26700436,"remaining_time":59.77915694},
{"learn":[0.01036863251],"iteration":585,"passed_time":84.4013195,"remaining_time":59.62823596},
{"learn":[0.01034579508],"iteration":586,"passed_time":84.5508998,"remaining_time":59.48811179},
{"learn":[0.01033525587],"iteration":587,"passed_time":84.67795595,"remaining_time":59.33217322},
{"learn":[0.01032064383],"iteration":588,"passed_time":84.80598687,"remaining_time":59.17701291},
{"learn":[0.01030441815],"iteration":589,"passed_time":84.93312643,"remaining_time":59.02132515},
{"learn":[0.01029511401],"iteration":590,"passed_time":85.06126261,"remaining_time":58.8664237},
{"learn":[0.0102567527],"iteration":591,"passed_time":85.20321255,"remaining_time":58.72113298},
{"learn":[0.01023747655],"iteration":592,"passed_time":85.33457605,"remaining_time":58.56858761},
{"learn":[0.01017735831],"iteration":593,"passed_time":85.49812697,"remaining_time":58.43811372},
{"learn":[0.01017734173],"iteration":594,"passed_time":85.6139417,"remaining_time":58.27503595},
{"learn":[0.01015370494],"iteration":595,"passed_time":85.7657113,"remaining_time":58.13648887},
{"learn":[0.01015371363],"iteration":596,"passed_time":85.88028082,"remaining_time":57.97278588},
{"learn":[0.01012052957],"iteration":597,"passed_time":86.02328537,"remaining_time":57.8283624},
{"learn":[0.01009963644],"iteration":598,"passed_time":86.16661877,"remaining_time":57.68416382},
{"learn":[0.01008983241],"iteration":599,"passed_time":86.32126882,"remaining_time":57.54751255},
{"learn":[0.01007221512],"iteration":600,"passed_time":86.46038209,"remaining_time":57.40048661},
{"learn":[0.01005723658],"iteration":601,"passed_time":86.60796421,"remaining_time":57.25908597},
{"learn":[0.01004393019],"iteration":602,"passed_time":86.75212792,"remaining_time":57.11541424},
{"learn":[0.01002550169],"iteration":603,"passed_time":86.89884204,"remaining_time":56.973413},
{"learn":[0.009993864449],"iteration":604,"passed_time":87.05759644,"remaining_time":56.83925718},
{"learn":[0.009966120523],"iteration":605,"passed_time":87.19817442,"remaining_time":56.69320251},
{"learn":[0.009939895266],"iteration":606,"passed_time":87.37034371,"remaining_time":56.56761957},
{"learn":[0.009923013782],"iteration":607,"passed_time":87.51460192,"remaining_time":56.42388808},
{"learn":[0.009887515684],"iteration":608,"passed_time":87.66921177,"remaining_time":56.28680099},
{"learn":[0.009863400218],"iteration":609,"passed_time":87.82014212,"remaining_time":56.14730398},
{"learn":[0.009837411188],"iteration":610,"passed_time":87.96992746,"remaining_time":56.00704056},
{"learn":[0.009837404955],"iteration":611,"passed_time":88.10190358,"remaining_time":55.85545521},
{"learn":[0.009829361246],"iteration":612,"passed_time":88.23815433,"remaining_time":55.7066325},
{"learn":[0.009800727512],"iteration":613,"passed_time":88.37997236,"remaining_time":55.5613507},
{"learn":[0.009779968641],"iteration":614,"passed_time":88.52925491,"remaining_time":55.42075308},
{"learn":[0.009757914295],"iteration":615,"passed_time":88.68525309,"remaining_time":55.28431361},
{"learn":[0.009717392076],"iteration":616,"passed_time":88.84103542,"remaining_time":55.14767677},
{"learn":[0.009671511318],"iteration":617,"passed_time":88.99617363,"remaining_time":55.01057982},
{"learn":[0.009651560561],"iteration":618,"passed_time":89.14730493,"remaining_time":54.87095828},
{"learn":[0.009623470559],"iteration":619,"passed_time":89.29681134,"remaining_time":54.73030372},
{"learn":[0.009623467557],"iteration":620,"passed_time":89.42953123,"remaining_time":54.57937574},
{"learn":[0.009617367607],"iteration":621,"passed_time":89.56018049,"remaining_time":54.42724795},
{"learn":[0.009586204791],"iteration":622,"passed_time":89.7281369,"remaining_time":54.29776503},
{"learn":[0.009548783623],"iteration":623,"passed_time":89.88142691,"remaining_time":54.15932134},
{"learn":[0.009539351386],"iteration":624,"passed_time":90.01534404,"remaining_time":54.00920642},
{"learn":[0.009514001666],"iteration":625,"passed_time":90.16306142,"remaining_time":53.86738814},
{"learn":[0.009494581834],"iteration":626,"passed_time":90.30925067,"remaining_time":53.72464195},
{"learn":[0.009476210463],"iteration":627,"passed_time":90.4460798,"remaining_time":53.57634026},
{"learn":[0.00945050452],"iteration":628,"passed_time":90.59471266,"remaining_time":53.4350372},
{"learn":[0.009430354256],"iteration":629,"passed_time":90.73103271,"remaining_time":53.28647953},
{"learn":[0.009407299395],"iteration":630,"passed_time":90.88861583,"remaining_time":53.15039499},
{"learn":[0.009366726248],"iteration":631,"passed_time":91.05108252,"remaining_time":53.01708603},
{"learn":[0.009366719725],"iteration":632,"passed_time":91.1654173,"remaining_time":52.85577907},
{"learn":[0.009366708271],"iteration":633,"passed_time":91.29053529,"remaining_time":52.70084529},
{"learn":[0.009350748636],"iteration":634,"passed_time":91.43291716,"remaining_time":52.55592876},
{"learn":[0.00935070143],"iteration":635,"passed_time":91.56552731,"remaining_time":52.40542758},
{"learn":[0.009328470872],"iteration":636,"passed_time":91.70233546,"remaining_time":52.25737484},
{"learn":[0.009313326908],"iteration":637,"passed_time":91.86004303,"remaining_time":52.12121564},
{"learn":[0.009305137937],"iteration":638,"passed_time":92.0051616,"remaining_time":51.9778769},
{"learn":[0.009305105562],"iteration":639,"passed_time":92.13814822,"remaining_time":51.82770838},
{"learn":[0.009291474272],"iteration":640,"passed_time":92.29830502,"remaining_time":51.69281046},
{"learn":[0.009278159212],"iteration":641,"passed_time":92.43717622,"remaining_time":51.54596431},
{"learn":[0.009261598173],"iteration":642,"passed_time":92.57924995,"remaining_time":51.40092104},
{"learn":[0.009238750072],"iteration":643,"passed_time":92.73234846,"remaining_time":51.26198144},
{"learn":[0.009225056175],"iteration":644,"passed_time":92.88888542,"remaining_time":51.12489042},
{"learn":[0.009209448305],"iteration":645,"passed_time":93.03551567,"remaining_time":50.98231045},
{"learn":[0.009197339657],"iteration":646,"passed_time":93.18270505,"remaining_time":50.840023},
{"learn":[0.009176197324],"iteration":647,"passed_time":93.3371515,"remaining_time":50.70166254},
{"learn":[0.009166363341],"iteration":648,"passed_time":93.47169491,"remaining_time":50.55248831},
{"learn":[0.009155480382],"iteration":649,"passed_time":93.63166142,"remaining_time":50.41704846},
{"learn":[0.009142396986],"iteration":650,"passed_time":93.78122436,"remaining_time":50.27595591},
{"learn":[0.009097191339],"iteration":651,"passed_time":93.94677336,"remaining_time":50.14336983},
{"learn":[0.00907407492],"iteration":652,"passed_time":94.10164485,"remaining_time":50.00500883},
{"learn":[0.009064457472],"iteration":653,"passed_time":94.23397279,"remaining_time":49.85467062},
{"learn":[0.009045254429],"iteration":654,"passed_time":94.37552537,"remaining_time":49.70924619},
{"learn":[0.009033329791],"iteration":655,"passed_time":94.51339431,"remaining_time":49.5619019},
{"learn":[0.009033304639],"iteration":656,"passed_time":94.62522462,"remaining_time":49.40099246},
{"learn":[0.009020278068],"iteration":657,"passed_time":94.7691331,"remaining_time":49.25690505},
{"learn":[0.009013831777],"iteration":658,"passed_time":94.89484602,"remaining_time":49.10340287},
{"learn":[0.009013809859],"iteration":659,"passed_time":94.99966089,"remaining_time":48.93921924},
{"learn":[0.008994692841],"iteration":660,"passed_time":95.15771452,"remaining_time":48.80251925},
{"learn":[0.008994691761],"iteration":661,"passed_time":95.26219884,"remaining_time":48.63840364},
{"learn":[0.008975234616],"iteration":662,"passed_time":95.39289622,"remaining_time":48.48779189},
{"learn":[0.008956332694],"iteration":663,"passed_time":95.544403,"remaining_time":48.34777019},
{"learn":[0.00893124623],"iteration":664,"passed_time":95.68667403,"remaining_time":48.20306135},
{"learn":[0.008931238755],"iteration":665,"passed_time":95.79986138,"remaining_time":48.04377433},
{"learn":[0.008873196836],"iteration":666,"passed_time":95.96322711,"remaining_time":47.9096771},
{"learn":[0.008873196836],"iteration":667,"passed_time":96.08549937,"remaining_time":47.75506855},
{"learn":[0.008873174124],"iteration":668,"passed_time":96.21542475,"remaining_time":47.60434319},
{"learn":[0.008834913704],"iteration":669,"passed_time":96.34374966,"remaining_time":47.45289162},
{"learn":[0.008826473623],"iteration":670,"passed_time":96.48051609,"remaining_time":47.30564798},
{"learn":[0.008809678612],"iteration":671,"passed_time":96.61809703,"remaining_time":47.15883307},
{"learn":[0.008798866511],"iteration":672,"passed_time":96.75389986,"remaining_time":47.01118165},
{"learn":[0.008790600334],"iteration":673,"passed_time":96.88346245,"remaining_time":46.86054712},
{"learn":[0.00877148311],"iteration":674,"passed_time":97.01669066,"remaining_time":46.71173995},
{"learn":[0.008740405],"iteration":675,"passed_time":97.15667912,"remaining_time":46.56621899},
{"learn":[0.00874039181],"iteration":676,"passed_time":97.26962895,"remaining_time":46.40781411},
{"learn":[0.008740372072],"iteration":677,"passed_time":97.39094943,"remaining_time":46.25351875},
{"learn":[0.008740358211],"iteration":678,"passed_time":97.51240524,"remaining_time":46.09938451},
{"learn":[0.008734101367],"iteration":679,"passed_time":97.63569794,"remaining_time":45.94621079},
{"learn":[0.008714251539],"iteration":680,"passed_time":97.77141876,"remaining_time":45.79894653},
{"learn":[0.008703812207],"iteration":681,"passed_time":97.90671141,"remaining_time":45.65151646},
{"learn":[0.008671207081],"iteration":682,"passed_time":98.05269446,"remaining_time":45.50908366},
{"learn":[0.008666778137],"iteration":683,"passed_time":98.18049705,"remaining_time":45.35824133},
{"learn":[0.008666771206],"iteration":684,"passed_time":98.30467684,"remaining_time":45.2058003},
{"learn":[0.008655672869],"iteration":685,"passed_time":98.45121052,"remaining_time":45.06367362},
{"learn":[0.008655301167],"iteration":686,"passed_time":98.57449556,"remaining_time":44.91094194},
{"learn":[0.008617851521],"iteration":687,"passed_time":98.73181978,"remaining_time":44.77373223},
{"learn":[0.008609992869],"iteration":688,"passed_time":98.86093545,"remaining_time":44.62373139},
{"learn":[0.008585159706],"iteration":689,"passed_time":99.00755817,"remaining_time":44.48165657},
{"learn":[0.00857673963],"iteration":690,"passed_time":99.13707841,"remaining_time":44.33192074},
{"learn":[0.008560341955],"iteration":691,"passed_time":99.2958447,"remaining_time":44.19526036},
{"learn":[0.008560337873],"iteration":692,"passed_time":99.41500051,"remaining_time":44.04098868},
{"learn":[0.008548333052],"iteration":693,"passed_time":99.62948245,"remaining_time":43.92884961},
{"learn":[0.008541282685],"iteration":694,"passed_time":99.75422962,"remaining_time":43.77703602},
{"learn":[0.008530943755],"iteration":695,"passed_time":99.89298421,"remaining_time":43.63141839},
{"learn":[0.008509331676],"iteration":696,"passed_time":100.0400842,"remaining_time":43.48944835},
{"learn":[0.008479148479],"iteration":697,"passed_time":100.2004476,"remaining_time":43.35320226},
{"learn":[0.008450833433],"iteration":698,"passed_time":100.3476151,"remaining_time":43.21120477},
{"learn":[0.008450838068],"iteration":699,"passed_time":100.4788593,"remaining_time":43.06236827},
{"learn":[0.008450838068],"iteration":700,"passed_time":100.6122608,"remaining_time":42.91450211},
{"learn":[0.00845083207],"iteration":701,"passed_time":100.7403104,"remaining_time":42.76440527},
{"learn":[0.008450832206],"iteration":702,"passed_time":100.8662115,"remaining_time":42.61346346},
{"learn":[0.008437689676],"iteration":703,"passed_time":101.0007403,"remaining_time":42.46622036},
{"learn":[0.008429692061],"iteration":704,"passed_time":101.1406537,"remaining_time":42.32126644},
{"learn":[0.008429678582],"iteration":705,"passed_time":101.267728,"remaining_time":42.17098021},
{"learn":[0.008429669492],"iteration":706,"passed_time":101.3950222,"remaining_time":42.02085077},
{"learn":[0.008406135866],"iteration":707,"passed_time":101.528299,"remaining_time":41.87325327},
{"learn":[0.008406125789],"iteration":708,"passed_time":101.6417671,"remaining_time":41.71756589},
{"learn":[0.008389861714],"iteration":709,"passed_time":101.778393,"remaining_time":41.57145631},
{"learn":[0.008368240918],"iteration":710,"passed_time":101.91851,"remaining_time":41.42679238},
{"learn":[0.008343021031],"iteration":711,"passed_time":102.0680961,"remaining_time":41.28597144},
{"learn":[0.008325030161],"iteration":712,"passed_time":102.2028391,"remaining_time":41.13915124},
{"learn":[0.008310163971],"iteration":713,"passed_time":102.3392707,"remaining_time":40.9930412},
{"learn":[0.008310163971],"iteration":714,"passed_time":102.4617117,"remaining_time":40.84138158},
{"learn":[0.008300669601],"iteration":715,"passed_time":102.5923655,"remaining_time":40.69306119},
{"learn":[0.008300669601],"iteration":716,"passed_time":102.7201092,"remaining_time":40.54364144},
{"learn":[0.008297477845],"iteration":717,"passed_time":102.8406427,"remaining_time":40.39145018},
{"learn":[0.008297466441],"iteration":718,"passed_time":102.9585317,"remaining_time":40.2383135},
{"learn":[0.008297466824],"iteration":719,"passed_time":103.0904548,"remaining_time":40.09073242},
{"learn":[0.008297455794],"iteration":720,"passed_time":103.22877,"remaining_time":39.94566828},
{"learn":[0.0082974396],"iteration":721,"passed_time":103.3539746,"remaining_time":39.79557471},
{"learn":[0.008297431291],"iteration":722,"passed_time":103.4757042,"remaining_time":39.64421861},
{"learn":[0.008297426393],"iteration":723,"passed_time":103.6039367,"remaining_time":39.4954234},
{"learn":[0.008277714689],"iteration":724,"passed_time":103.7478544,"remaining_time":39.35263444},
{"learn":[0.008259354953],"iteration":725,"passed_time":103.8906427,"remaining_time":39.2094161},
{"learn":[0.008259353048],"iteration":726,"passed_time":104.0172563,"remaining_time":39.06012514},
{"learn":[0.008259331822],"iteration":727,"passed_time":104.1395997,"remaining_time":38.909301},
{"learn":[0.008259309652],"iteration":728,"passed_time":104.2565579,"remaining_time":38.75655308},
{"learn":[0.008244779221],"iteration":729,"passed_time":104.3888931,"remaining_time":38.60959059},
{"learn":[0.008244773787],"iteration":730,"passed_time":104.5120429,"remaining_time":38.45928803},
{"learn":[0.008241780285],"iteration":731,"passed_time":104.6435588,"remaining_time":38.31212263},
{"learn":[0.008201558813],"iteration":732,"passed_time":104.7919556,"remaining_time":38.17114889},
{"learn":[0.00818074627],"iteration":733,"passed_time":104.9424424,"remaining_time":38.03091238},
{"learn":[0.008146296628],"iteration":734,"passed_time":105.0816006,"remaining_time":37.88656347},
{"learn":[0.00814629065],"iteration":735,"passed_time":105.2147431,"remaining_time":37.74007091},
{"learn":[0.008112909434],"iteration":736,"passed_time":105.3679611,"remaining_time":37.60077851},
{"learn":[0.008102653978],"iteration":737,"passed_time":105.5106977,"remaining_time":37.45772736},
{"learn":[0.008095910115],"iteration":738,"passed_time":105.6398335,"remaining_time":37.30987352},
{"learn":[0.008087582417],"iteration":739,"passed_time":105.7849591,"remaining_time":37.16768834},
{"learn":[0.008066326993],"iteration":740,"passed_time":105.9345282,"remaining_time":37.02704834},
{"learn":[0.00805572628],"iteration":741,"passed_time":106.0745286,"remaining_time":36.88305712},
{"learn":[0.00804495562],"iteration":742,"passed_time":106.2201265,"remaining_time":36.74101279},
{"learn":[0.008040186248],"iteration":743,"passed_time":106.3361919,"remaining_time":36.58879723},
{"learn":[0.008003205975],"iteration":744,"passed_time":106.467915,"remaining_time":36.44203803},
{"learn":[0.007998464661],"iteration":745,"passed_time":106.5948352,"remaining_time":36.29368383},
{"learn":[0.007998460851],"iteration":746,"passed_time":106.7147,"remaining_time":36.14299746},
{"learn":[0.007990875385],"iteration":747,"passed_time":106.8423699,"remaining_time":35.99502303},
{"learn":[0.007974013323],"iteration":748,"passed_time":106.9912019,"remaining_time":35.85419451},
{"learn":[0.007968000445],"iteration":749,"passed_time":107.1186414,"remaining_time":35.70621381},
{"learn":[0.007952023115],"iteration":750,"passed_time":107.2605671,"remaining_time":35.56309082},
{"learn":[0.007935538781],"iteration":751,"passed_time":107.3948446,"remaining_time":35.41744874},
{"learn":[0.007924710682],"iteration":752,"passed_time":107.5412647,"remaining_time":35.27581988},
{"learn":[0.007915546798],"iteration":753,"passed_time":107.6723016,"remaining_time":35.12915942},
{"learn":[0.007903558443],"iteration":754,"passed_time":107.825308,"remaining_time":34.98966948},
{"learn":[0.00790354823],"iteration":755,"passed_time":107.9431854,"remaining_time":34.83880585},
{"learn":[0.00790352822],"iteration":756,"passed_time":108.0598614,"remaining_time":34.68764375},
{"learn":[0.007896182038],"iteration":757,"passed_time":108.1975135,"remaining_time":34.54326947},
{"learn":[0.00789617032],"iteration":758,"passed_time":108.3117592,"remaining_time":34.39148086},
{"learn":[0.007896169367],"iteration":759,"passed_time":108.4168645,"remaining_time":34.23690458},
{"learn":[0.00789612446],"iteration":760,"passed_time":108.5236748,"remaining_time":34.08299378},
{"learn":[0.00788961399],"iteration":761,"passed_time":108.6426739,"remaining_time":33.93301364},
{"learn":[0.007883426629],"iteration":762,"passed_time":108.7705281,"remaining_time":33.7858652},
{"learn":[0.00786036974],"iteration":763,"passed_time":108.9094545,"remaining_time":33.64218753},
{"learn":[0.007845308686],"iteration":764,"passed_time":109.0574147,"remaining_time":33.50129731},
{"learn":[0.007845308805],"iteration":765,"passed_time":109.2050133,"remaining_time":33.36027821},
{"learn":[0.007845310991],"iteration":766,"passed_time":109.3230815,"remaining_time":33.21027117},
{"learn":[0.007828670427],"iteration":767,"passed_time":109.4792689,"remaining_time":33.07186248},
{"learn":[0.007808549943],"iteration":768,"passed_time":109.6185304,"remaining_time":32.92832317},
{"learn":[0.007804470746],"iteration":769,"passed_time":109.7392976,"remaining_time":32.77927071},
{"learn":[0.007779615547],"iteration":770,"passed_time":109.8847128,"remaining_time":32.6376125},
{"learn":[0.007779612273],"iteration":771,"passed_time":110.0167289,"remaining_time":32.49198729},
{"learn":[0.007771820273],"iteration":772,"passed_time":110.1564587,"remaining_time":32.34866251},
{"learn":[0.007746476337],"iteration":773,"passed_time":110.2895071,"remaining_time":32.20339614},
{"learn":[0.007739176843],"iteration":774,"passed_time":110.4197512,"remaining_time":32.05734712},
{"learn":[0.007739145545],"iteration":775,"passed_time":110.5519947,"remaining_time":31.911916},
{"learn":[0.007739141183],"iteration":776,"passed_time":110.6774673,"remaining_time":31.76457556},
{"learn":[0.00772027605],"iteration":777,"passed_time":110.8280381,"remaining_time":31.62445302},
{"learn":[0.007708247501],"iteration":778,"passed_time":110.971438,"remaining_time":31.48226932},
{"learn":[0.007695366998],"iteration":779,"passed_time":111.1149137,"remaining_time":31.34010386},
{"learn":[0.007685502376],"iteration":780,"passed_time":111.2588638,"remaining_time":31.19806807},
{"learn":[0.007676687086],"iteration":781,"passed_time":111.3889792,"remaining_time":31.05217067},
{"learn":[0.007658496944],"iteration":782,"passed_time":111.5485017,"remaining_time":30.91446343},
{"learn":[0.007651258294],"iteration":783,"passed_time":111.6798299,"remaining_time":30.76893272},
{"learn":[0.007638902378],"iteration":784,"passed_time":111.8112836,"remaining_time":30.62347259},
{"learn":[0.007638437506],"iteration":785,"passed_time":111.9498411,"remaining_time":30.47998217},
{"learn":[0.007633396147],"iteration":786,"passed_time":112.0761893,"remaining_time":30.3331999},
{"learn":[0.007633396147],"iteration":787,"passed_time":112.208553,"remaining_time":30.18808785},
{"learn":[0.007633396147],"iteration":788,"passed_time":112.3299308,"remaining_time":30.04007021},
{"learn":[0.00763339084],"iteration":789,"passed_time":112.4441636,"remaining_time":29.8902207},
{"learn":[0.007633380491],"iteration":790,"passed_time":112.5658969,"remaining_time":29.74244305},
{"learn":[0.007633372888],"iteration":791,"passed_time":112.6936508,"remaining_time":29.59631233},
{"learn":[0.007633301746],"iteration":792,"passed_time":112.8160699,"remaining_time":29.44883539},
{"learn":[0.007633290019],"iteration":793,"passed_time":112.9424942,"remaining_time":29.30246072},
{"learn":[0.007633290019],"iteration":794,"passed_time":113.0638326,"remaining_time":29.15482477},
{"learn":[0.007633257772],"iteration":795,"passed_time":113.1853676,"remaining_time":29.00730526},
{"learn":[0.007633246071],"iteration":796,"passed_time":113.3090708,"remaining_time":28.86040323},
{"learn":[0.007633239948],"iteration":797,"passed_time":113.4203351,"remaining_time":28.71041063},
{"learn":[0.007633225397],"iteration":798,"passed_time":113.5505933,"remaining_time":28.56529319},
{"learn":[0.007633230296],"iteration":799,"passed_time":113.6744465,"remaining_time":28.41861163},
{"learn":[0.00763063015],"iteration":800,"passed_time":113.7938006,"remaining_time":28.2708693},
{"learn":[0.007612731285],"iteration":801,"passed_time":113.9317841,"remaining_time":28.12779707},
{"learn":[0.00761272444],"iteration":802,"passed_time":114.0570232,"remaining_time":27.98161091},
{"learn":[0.007611149281],"iteration":803,"passed_time":114.1823338,"remaining_time":27.83549431},
{"learn":[0.007611141108],"iteration":804,"passed_time":114.3076003,"remaining_time":27.68941871},
{"learn":[0.007611138795],"iteration":805,"passed_time":114.4289332,"remaining_time":27.54244794},
{"learn":[0.007611090093],"iteration":806,"passed_time":114.5611888,"remaining_time":27.39815297},
{"learn":[0.007611077847],"iteration":807,"passed_time":114.6847058,"remaining_time":27.25181127},
{"learn":[0.007611083842],"iteration":808,"passed_time":114.8021982,"remaining_time":27.10410365},
{"learn":[0.007610390882],"iteration":809,"passed_time":114.918815,"remaining_time":26.95626525},
{"learn":[0.00761035441],"iteration":810,"passed_time":115.0567192,"remaining_time":26.81346478},
{"learn":[0.007610332929],"iteration":811,"passed_time":115.1872319,"remaining_time":26.66896503},
{"learn":[0.007610330463],"iteration":812,"passed_time":115.3203446,"remaining_time":26.52509771},
{"learn":[0.007610321755],"iteration":813,"passed_time":115.4485156,"remaining_time":26.38012765},
{"learn":[0.007610316176],"iteration":814,"passed_time":115.5837699,"remaining_time":26.23680667},
{"learn":[0.007610306913],"iteration":815,"passed_time":115.7134066,"remaining_time":26.09223874},
{"learn":[0.007610302451],"iteration":816,"passed_time":115.8236043,"remaining_time":25.94335323},
{"learn":[0.007610300818],"iteration":817,"passed_time":115.9515112,"remaining_time":25.79850249},
{"learn":[0.007610276446],"iteration":818,"passed_time":116.0714171,"remaining_time":25.6519249},
{"learn":[0.007610237525],"iteration":819,"passed_time":116.2058002,"remaining_time":25.5085903},
{"learn":[0.007610193568],"iteration":820,"passed_time":116.3343676,"remaining_time":25.36400951},
{"learn":[0.007610180268],"iteration":821,"passed_time":116.4496532,"remaining_time":25.21659156},
{"learn":[0.00761014228],"iteration":822,"passed_time":116.5808947,"remaining_time":25.0726833},
{"learn":[0.007610088813],"iteration":823,"passed_time":116.7174362,"remaining_time":24.92993783},
{"learn":[0.007610069911],"iteration":824,"passed_time":116.8507212,"remaining_time":24.78651663},
{"learn":[0.007610054545],"iteration":825,"passed_time":116.9882308,"remaining_time":24.64400987},
{"learn":[0.00761003888],"iteration":826,"passed_time":117.1297177,"remaining_time":24.50234724},
{"learn":[0.007610002956],"iteration":827,"passed_time":117.2647553,"remaining_time":24.3593453},
{"learn":[0.007609980378],"iteration":828,"passed_time":117.4027001,"remaining_time":24.21696226},
{"learn":[0.007609978873],"iteration":829,"passed_time":117.5115194,"remaining_time":24.06862446},
{"learn":[0.007578326159],"iteration":830,"passed_time":117.6741292,"remaining_time":23.9313211},
{"learn":[0.007578322613],"iteration":831,"passed_time":117.7974801,"remaining_time":23.78602964},
{"learn":[0.007578281811],"iteration":832,"passed_time":117.9184023,"remaining_time":23.64030393},
{"learn":[0.007555282259],"iteration":833,"passed_time":118.0664229,"remaining_time":23.50003142},
{"learn":[0.007538694364],"iteration":834,"passed_time":118.2158565,"remaining_time":23.36001955},
{"learn":[0.007538690154],"iteration":835,"passed_time":118.3359852,"remaining_time":23.21423634},
{"learn":[0.007538678717],"iteration":836,"passed_time":118.4657753,"remaining_time":23.07039591},
{"learn":[0.00753866375],"iteration":837,"passed_time":118.5983177,"remaining_time":22.92712108},
{"learn":[0.007538588265],"iteration":838,"passed_time":118.7262613,"remaining_time":22.78298936},
{"learn":[0.007538585119],"iteration":839,"passed_time":118.8555927,"remaining_time":22.63916051},
{"learn":[0.007538569738],"iteration":840,"passed_time":118.983378,"remaining_time":22.49507385},
{"learn":[0.007538539274],"iteration":841,"passed_time":119.1148813,"remaining_time":22.35172357},
{"learn":[0.007538526075],"iteration":842,"passed_time":119.2459997,"remaining_time":22.20832971},
{"learn":[0.0075385269],"iteration":843,"passed_time":119.3753077,"remaining_time":22.06463034},
{"learn":[0.007538516007],"iteration":844,"passed_time":119.5013759,"remaining_time":21.92037073},
{"learn":[0.007538506346],"iteration":845,"passed_time":119.6326786,"remaining_time":21.77710699},
{"learn":[0.007538507843],"iteration":846,"passed_time":119.7629318,"remaining_time":21.63368189},
{"learn":[0.007538499016],"iteration":847,"passed_time":119.8925925,"remaining_time":21.49018167},
{"learn":[0.00753849234],"iteration":848,"passed_time":120.0228998,"remaining_time":21.34682906},
{"learn":[0.007538473175],"iteration":849,"passed_time":120.1573394,"remaining_time":21.20423636},
{"learn":[0.007538473175],"iteration":850,"passed_time":120.2816681,"remaining_time":21.05989254},
{"learn":[0.007538473175],"iteration":851,"passed_time":120.4125334,"remaining_time":20.91673115},
{"learn":[0.007527110554],"iteration":852,"passed_time":120.5488375,"remaining_time":20.77453589},
{"learn":[0.007527097234],"iteration":853,"passed_time":120.6918344,"remaining_time":20.63349862},
{"learn":[0.00752708062],"iteration":854,"passed_time":120.8259438,"remaining_time":20.49094953},
{"learn":[0.00745721673],"iteration":855,"passed_time":120.9881593,"remaining_time":20.3531483},
{"learn":[0.007444377275],"iteration":856,"passed_time":121.1236402,"remaining_time":20.21082912},
{"learn":[0.007423880142],"iteration":857,"passed_time":121.2731943,"remaining_time":20.070855},
{"learn":[0.007411387516],"iteration":858,"passed_time":121.427497,"remaining_time":19.93163804},
{"learn":[0.007387984157],"iteration":859,"passed_time":121.5814867,"remaining_time":19.79233504},
{"learn":[0.007374487632],"iteration":860,"passed_time":121.732509,"remaining_time":19.65251888},
{"learn":[0.007360958138],"iteration":861,"passed_time":121.8749655,"remaining_time":19.51130538},
{"learn":[0.007353467765],"iteration":862,"passed_time":122.008443,"remaining_time":19.3686636},
{"learn":[0.00733122886],"iteration":863,"passed_time":122.1642852,"remaining_time":19.22956342},
{"learn":[0.007322450085],"iteration":864,"passed_time":122.3068684,"remaining_time":19.08835518},
{"learn":[0.007299142637],"iteration":865,"passed_time":122.4492754,"remaining_time":18.94711651},
{"learn":[0.007293239883],"iteration":866,"passed_time":122.5910066,"remaining_time":18.80577148},
{"learn":[0.007274330081],"iteration":867,"passed_time":122.7451818,"remaining_time":18.66631797},
{"learn":[0.007250729338],"iteration":868,"passed_time":122.8786753,"remaining_time":18.52371285},
{"learn":[0.007241866498],"iteration":869,"passed_time":123.0112194,"remaining_time":18.38098681},
{"learn":[0.007231857429],"iteration":870,"passed_time":123.1511689,"remaining_time":18.23938092},
{"learn":[0.007220091019],"iteration":871,"passed_time":123.3019165,"remaining_time":18.09936389},
{"learn":[0.007220082609],"iteration":872,"passed_time":123.408151,"remaining_time":17.95284671},
{"learn":[0.007220073354],"iteration":873,"passed_time":123.5298224,"remaining_time":17.80864717},
{"learn":[0.007220067478],"iteration":874,"passed_time":123.6374455,"remaining_time":17.66249221},
{"learn":[0.007220064102],"iteration":875,"passed_time":123.7412091,"remaining_time":17.51587891},
{"learn":[0.007220022049],"iteration":876,"passed_time":123.8572075,"remaining_time":17.37107928},
{"learn":[0.007220009123],"iteration":877,"passed_time":123.9806837,"remaining_time":17.22738429},
{"learn":[0.00722001579],"iteration":878,"passed_time":124.0888253,"remaining_time":17.08162442},
{"learn":[0.007215753288],"iteration":879,"passed_time":124.2191303,"remaining_time":16.93897231},
{"learn":[0.007215754632],"iteration":880,"passed_time":124.3439437,"remaining_time":16.79560648},
{"learn":[0.00721572948],"iteration":881,"passed_time":124.5633518,"remaining_time":16.66493823},
{"learn":[0.007215732201],"iteration":882,"passed_time":124.7466039,"remaining_time":16.5292782},
{"learn":[0.007215730016],"iteration":883,"passed_time":124.934135,"remaining_time":16.39407202},
{"learn":[0.007215730441],"iteration":884,"passed_time":125.0543887,"remaining_time":16.25000531},
{"learn":[0.00721572908],"iteration":885,"passed_time":125.1852239,"remaining_time":16.10735386},
{"learn":[0.007214996779],"iteration":886,"passed_time":125.3410283,"remaining_time":15.96791004},
{"learn":[0.007214995282],"iteration":887,"passed_time":125.4694697,"remaining_time":15.82497817},
{"learn":[0.007214999228],"iteration":888,"passed_time":125.5919829,"remaining_time":15.6813387},
{"learn":[0.007214982509],"iteration":889,"passed_time":125.7316486,"remaining_time":15.53986668},
{"learn":[0.007214971071],"iteration":890,"passed_time":125.8738876,"remaining_time":15.39871352},
{"learn":[0.007209527064],"iteration":891,"passed_time":126.0063596,"remaining_time":15.25637538},
{"learn":[0.007206391296],"iteration":892,"passed_time":126.1493715,"remaining_time":15.11532223},
{"learn":[0.007206394833],"iteration":893,"passed_time":126.2859228,"remaining_time":14.97349868},
{"learn":[0.007197271955],"iteration":894,"passed_time":126.4394203,"remaining_time":14.83367501},
{"learn":[0.007174696675],"iteration":895,"passed_time":126.600356,"remaining_time":14.69468418},
{"learn":[0.007174666741],"iteration":896,"passed_time":126.7257507,"remaining_time":14.55156334},
{"learn":[0.007159554543],"iteration":897,"passed_time":126.8712044,"remaining_time":14.41076041},
{"learn":[0.007150002255],"iteration":898,"passed_time":127.0312567,"remaining_time":14.27158723},
{"learn":[0.00714350225],"iteration":899,"passed_time":127.4260881,"remaining_time":14.15845423},
{"learn":[0.007129596],"iteration":900,"passed_time":128.0335817,"remaining_time":14.06806281},
{"learn":[0.007119583566],"iteration":901,"passed_time":128.2129038,"remaining_time":13.93000507},
{"learn":[0.007109487944],"iteration":902,"passed_time":128.3494659,"remaining_time":13.78726267},
{"learn":[0.007100015323],"iteration":903,"passed_time":128.5826161,"remaining_time":13.65479109},
{"learn":[0.007087210215],"iteration":904,"passed_time":128.9517936,"remaining_time":13.53637613},
{"learn":[0.007073094571],"iteration":905,"passed_time":129.2060166,"remaining_time":13.40548075},
{"learn":[0.007073073756],"iteration":906,"passed_time":129.3455469,"remaining_time":13.26255332},
{"learn":[0.007073075525],"iteration":907,"passed_time":129.5770458,"remaining_time":13.12895177},
{"learn":[0.007073064903],"iteration":908,"passed_time":129.7296714,"remaining_time":12.98723883},
{"learn":[0.007073068994],"iteration":909,"passed_time":129.855988,"remaining_time":12.84289991},
{"learn":[0.007072800539],"iteration":910,"passed_time":129.9913202,"remaining_time":12.69948134},
{"learn":[0.007053212305],"iteration":911,"passed_time":130.1594042,"remaining_time":12.55924076},
{"learn":[0.007053212314],"iteration":912,"passed_time":130.3074696,"remaining_time":12.4170316},
{"learn":[0.007053198172],"iteration":913,"passed_time":130.4602721,"remaining_time":12.27525536},
{"learn":[0.007050011574],"iteration":914,"passed_time":130.6310572,"remaining_time":12.13512553},
{"learn":[0.007029273941],"iteration":915,"passed_time":131.1413494,"remaining_time":12.02606261},
{"learn":[0.007019504121],"iteration":916,"passed_time":131.3668706,"remaining_time":11.89034925},
{"learn":[0.007013786443],"iteration":917,"passed_time":131.5284489,"remaining_time":11.74872855},
{"learn":[0.007000997231],"iteration":918,"passed_time":131.6763323,"remaining_time":11.60585736},
{"learn":[0.006987870342],"iteration":919,"passed_time":131.8273606,"remaining_time":11.46324875},
{"learn":[0.006969058556],"iteration":920,"passed_time":131.9798903,"remaining_time":11.32075063},
{"learn":[0.006969030416],"iteration":921,"passed_time":132.1393142,"remaining_time":11.178814},
{"learn":[0.006969028366],"iteration":922,"passed_time":132.3543012,"remaining_time":11.04147475},
{"learn":[0.006969034778],"iteration":923,"passed_time":132.4852557,"remaining_time":10.89705567},
{"learn":[0.006969023885],"iteration":924,"passed_time":132.63186,"remaining_time":10.75393459},
{"learn":[0.006961636674],"iteration":925,"passed_time":132.7727963,"remaining_time":10.61035305},
{"learn":[0.006961637337],"iteration":926,"passed_time":132.9283187,"remaining_time":10.46792585},
{"learn":[0.006961619096],"iteration":927,"passed_time":133.0596786,"remaining_time":10.32359575},
{"learn":[0.006961611213],"iteration":928,"passed_time":133.1967569,"remaining_time":10.17973061},
{"learn":[0.006961614342],"iteration":929,"passed_time":133.3178864,"remaining_time":10.03467962},
{"learn":[0.006961602241],"iteration":930,"passed_time":133.4505119,"remaining_time":9.890532033},
{"learn":[0.006961441932],"iteration":931,"passed_time":133.5709034,"remaining_time":9.745516558},
{"learn":[0.006942443304],"iteration":932,"passed_time":133.7363128,"remaining_time":9.603786663},
{"learn":[0.006932123789],"iteration":933,"passed_time":133.8679774,"remaining_time":9.459621526},
{"learn":[0.006906313188],"iteration":934,"passed_time":134.0352823,"remaining_time":9.317960805},
{"learn":[0.006892626912],"iteration":935,"passed_time":134.1849481,"remaining_time":9.175039189},
{"learn":[0.006883800976],"iteration":936,"passed_time":134.3287146,"remaining_time":9.031706534},
{"learn":[0.006870095455],"iteration":937,"passed_time":134.4792705,"remaining_time":8.888821716},
{"learn":[0.006870089596],"iteration":938,"passed_time":134.6111281,"remaining_time":8.744705875},
{"learn":[0.00686690885],"iteration":939,"passed_time":134.7400303,"remaining_time":8.600427468},
{"learn":[0.006856419831],"iteration":940,"passed_time":134.9236426,"remaining_time":8.459612025},
{"learn":[0.006838573023],"iteration":941,"passed_time":135.086215,"remaining_time":8.317410264},
{"learn":[0.006829963671],"iteration":942,"passed_time":135.2609299,"remaining_time":8.17589926},
{"learn":[0.006829934678],"iteration":943,"passed_time":135.4290457,"remaining_time":8.033926438},
{"learn":[0.006829866385],"iteration":944,"passed_time":135.6423903,"remaining_time":7.894530652},
{"learn":[0.006829842979],"iteration":945,"passed_time":135.8849116,"remaining_time":7.756644002},
{"learn":[0.006829806775],"iteration":946,"passed_time":136.0941213,"remaining_time":7.616672046},
{"learn":[0.006829768697],"iteration":947,"passed_time":136.2647029,"remaining_time":7.474435179},
{"learn":[0.006829751272],"iteration":948,"passed_time":136.4112161,"remaining_time":7.330845123},
{"learn":[0.006829751689],"iteration":949,"passed_time":136.5444071,"remaining_time":7.186547741},
{"learn":[0.006814021424],"iteration":950,"passed_time":136.736294,"remaining_time":7.04529801},
{"learn":[0.006777327385],"iteration":951,"passed_time":136.9501663,"remaining_time":6.905050402},
{"learn":[0.006769272515],"iteration":952,"passed_time":137.1253395,"remaining_time":6.762739721},
{"learn":[0.006769268943],"iteration":953,"passed_time":137.2587049,"remaining_time":6.618344261},
{"learn":[0.006769258211],"iteration":954,"passed_time":137.3717376,"remaining_time":6.473013813},
{"learn":[0.006756957938],"iteration":955,"passed_time":137.5403199,"remaining_time":6.330307612},
{"learn":[0.006756939025],"iteration":956,"passed_time":137.743305,"remaining_time":6.189093119},
{"learn":[0.006756933319],"iteration":957,"passed_time":137.8937759,"remaining_time":6.045447376},
{"learn":[0.006756901772],"iteration":958,"passed_time":138.0364955,"remaining_time":5.901456011},
{"learn":[0.006756873859],"iteration":959,"passed_time":138.2454388,"remaining_time":5.760226616},
{"learn":[0.006756877805],"iteration":960,"passed_time":138.4185678,"remaining_time":5.617402857},
{"learn":[0.006756835361],"iteration":961,"passed_time":138.61291,"remaining_time":5.475354032},
{"learn":[0.006756837385],"iteration":962,"passed_time":138.7884073,"remaining_time":5.332472555},
{"learn":[0.006756835489],"iteration":963,"passed_time":138.9711181,"remaining_time":5.189792793},
{"learn":[0.006756798335],"iteration":964,"passed_time":139.1785501,"remaining_time":5.047926689},
{"learn":[0.006756730717],"iteration":965,"passed_time":139.3466619,"remaining_time":4.904540895},
{"learn":[0.006756717544],"iteration":966,"passed_time":139.4767847,"remaining_time":4.759807544},
{"learn":[0.006756368505],"iteration":967,"passed_time":139.6425438,"remaining_time":4.616282441},
{"learn":[0.006756352314],"iteration":968,"passed_time":139.7683343,"remaining_time":4.471432778},
{"learn":[0.006756334761],"iteration":969,"passed_time":139.9080945,"remaining_time":4.32705447},
{"learn":[0.006756313127],"iteration":970,"passed_time":140.0513289,"remaining_time":4.182789432},
{"learn":[0.006756267682],"iteration":971,"passed_time":140.1583993,"remaining_time":4.037484752},
{"learn":[0.006756267682],"iteration":972,"passed_time":140.2925554,"remaining_time":3.893010272},
{"learn":[0.006756266865],"iteration":973,"passed_time":140.417653,"remaining_time":3.748315171},
{"learn":[0.006756229737],"iteration":974,"passed_time":140.5345136,"remaining_time":3.603449067},
{"learn":[0.006756203204],"iteration":975,"passed_time":140.6700875,"remaining_time":3.459100512},
{"learn":[0.006756173678],"iteration":976,"passed_time":140.8069208,"remaining_time":3.314799568},
{"learn":[0.006756101689],"iteration":977,"passed_time":140.935334,"remaining_time":3.170324488},
{"learn":[0.006755644898],"iteration":978,"passed_time":141.0907548,"remaining_time":3.026461543},
{"learn":[0.006755644898],"iteration":979,"passed_time":141.2206851,"remaining_time":2.882054798},
{"learn":[0.006755581518],"iteration":980,"passed_time":141.3342326,"remaining_time":2.737360265},
{"learn":[0.006755542739],"iteration":981,"passed_time":141.4556164,"remaining_time":2.592872806},
{"learn":[0.006755473627],"iteration":982,"passed_time":141.5683121,"remaining_time":2.448282101},
{"learn":[0.006755441652],"iteration":983,"passed_time":141.6985888,"remaining_time":2.304042095},
{"learn":[0.006742985982],"iteration":984,"passed_time":141.8340215,"remaining_time":2.159908957},
{"learn":[0.006742957157],"iteration":985,"passed_time":141.9579535,"remaining_time":2.015630172},
{"learn":[0.00674295253],"iteration":986,"passed_time":142.0725043,"remaining_time":1.871269054},
{"learn":[0.00674293277],"iteration":987,"passed_time":142.1993828,"remaining_time":1.72711801},
{"learn":[0.006742929113],"iteration":988,"passed_time":142.3128416,"remaining_time":1.582852637},
{"learn":[0.006734216204],"iteration":989,"passed_time":142.463977,"remaining_time":1.439030071},
{"learn":[0.006728347213],"iteration":990,"passed_time":142.6064501,"remaining_time":1.295114077},
{"learn":[0.006721037527],"iteration":991,"passed_time":142.7717718,"remaining_time":1.151385257},
{"learn":[0.006710965348],"iteration":992,"passed_time":142.9162862,"remaining_time":1.007466267},
{"learn":[0.006710965348],"iteration":993,"passed_time":143.0727052,"remaining_time":0.863617939},
{"learn":[0.006698293573],"iteration":994,"passed_time":143.2388247,"remaining_time":0.7197930889},
{"learn":[0.006698282526],"iteration":995,"passed_time":143.3807112,"remaining_time":0.5758261495},
{"learn":[0.006698255869],"iteration":996,"passed_time":143.5152557,"remaining_time":0.4318412911},
{"learn":[0.006698250554],"iteration":997,"passed_time":143.6279157,"remaining_time":0.2878314944},
{"learn":[0.006698251515],"iteration":998,"passed_time":143.7356425,"remaining_time":0.143879522},
{"learn":[0.006698254109],"iteration":999,"passed_time":143.848546,"remaining_time":0}
]}